{"assets":{"08F420D27E33D0EC9CABBBFB1CBFCF70":{"type":"texture","index":8,"assetRequest":{"type":"slide","state":"contents","slide":"none"},"url":{"native":"assets\/C6FC5B5A-1020-4321-8905-82587C648825.pdf"},"width":442,"height":143},"599DC56368438AE14825012FB21F2616":{"type":"texture","index":3,"assetRequest":{"type":"slide","state":"contents","slide":"none"},"url":{"native":"assets\/C6FC5B5A-1020-4321-8905-82587C648825.pdf"},"width":620,"height":128},"DBD44AC5EC23EE3DF080EA173AE7C574":{"type":"texture","index":12,"assetRequest":{"type":"slide","state":"contents","slide":"none"},"url":{"native":"assets\/C6FC5B5A-1020-4321-8905-82587C648825.pdf"},"width":441,"height":143},"65279477319C7AF4FE443308577C43EE":{"type":"texture","index":14,"assetRequest":{"type":"slide","state":"contents","slide":"none"},"url":{"native":"assets\/C6FC5B5A-1020-4321-8905-82587C648825.pdf"},"width":1920,"height":1080},"370936F4C116E35A4E4E20C10E9D5053":{"type":"texture","index":13,"assetRequest":{"type":"slide","state":"contents","slide":"none"},"url":{"native":"assets\/C6FC5B5A-1020-4321-8905-82587C648825.pdf"},"width":34,"height":143},"9211CEF4A32EFCE19DDE0CF9CF6F5DB5":{"type":"texture","index":7,"assetRequest":{"type":"slide","state":"contents","slide":"none"},"url":{"native":"assets\/C6FC5B5A-1020-4321-8905-82587C648825.pdf"},"width":441,"height":143},"C9F81E9FC932E0891783B87EDE7E3B6E":{"type":"texture","index":4,"assetRequest":{"type":"slide","state":"contents","slide":"none"},"url":{"native":"assets\/C6FC5B5A-1020-4321-8905-82587C648825.pdf"},"width":620,"height":128},"C2A54592E8BA3E35D010F868277412E0":{"type":"texture","index":9,"assetRequest":{"type":"slide","state":"contents","slide":"none"},"url":{"native":"assets\/C6FC5B5A-1020-4321-8905-82587C648825.pdf"},"width":34,"height":143},"73E42203A74861E56ECA3E130B16097A":{"type":"texture","index":10,"assetRequest":{"type":"slide","state":"contents","slide":"none"},"url":{"native":"assets\/C6FC5B5A-1020-4321-8905-82587C648825.pdf"},"width":34,"height":124},"D4535E46D712DA438D540C50849987E9":{"type":"texture","index":11,"assetRequest":{"type":"slide","state":"contents","slide":"none"},"url":{"native":"assets\/C6FC5B5A-1020-4321-8905-82587C648825.pdf"},"width":441,"height":143},"0FEF2B786609238E24DCBD6FA003DA71":{"type":"texture","index":6,"assetRequest":{"type":"slide","state":"contents","slide":"none"},"url":{"native":"assets\/C6FC5B5A-1020-4321-8905-82587C648825.pdf"},"width":34,"height":124},"BD818B1FEA8AC6E7E678F89C18F5D64B":{"type":"texture","index":15,"assetRequest":{"type":"slide","state":"contents","slide":"none"},"url":{"native":"assets\/C6FC5B5A-1020-4321-8905-82587C648825.pdf"},"width":1920,"height":1080},"5299F162DC250DDCFDCD2A19147CC01B":{"type":"texture","index":5,"assetRequest":{"type":"slide","state":"contents","slide":"none"},"url":{"native":"assets\/C6FC5B5A-1020-4321-8905-82587C648825.pdf"},"width":1926,"height":180},"00EF00B3FF14D579613EFF71EF05F5D2":{"type":"texture","index":1,"assetRequest":{"type":"slide","state":"contents","slide":"none"},"url":{"native":"assets\/C6FC5B5A-1020-4321-8905-82587C648825.pdf"},"width":620,"height":129},"453BE8B0F2DA81A5A63782E720315E21":{"type":"texture","index":2,"assetRequest":{"type":"slide","state":"contents","slide":"none"},"url":{"native":"assets\/C6FC5B5A-1020-4321-8905-82587C648825.pdf"},"width":620,"height":128},"63320DF3585E5970F64F12FDA3FAB4CB":{"type":"texture","index":0,"assetRequest":{"type":"slide","state":"contents","slide":"none"},"url":{"native":"assets\/C6FC5B5A-1020-4321-8905-82587C648825.pdf"},"width":1920,"height":1080}},"events":[{"effects":[{"beginTime":0,"baseLayer":{"animations":[],"initialState":{"affineTransform":[1,0,0,1,0,0],"masksToBounds":false,"rotation":0,"scale":1,"position":{"pointX":961.30000000000007,"pointY":238.60000000000002},"width":34,"sublayerTransform":[1,0,0,0,0,1,0,0,0,0,1,0,0,0,0,1],"contentsRect":{"y":0,"x":0,"width":1,"height":1},"opacity":1,"edgeAntialiasingMask":251658240,"height":124,"hidden":false,"anchorPoint":{"pointX":0.5,"pointY":0.5}},"objectID":"B40CEB66-27F9-4E74-BF73-EE1640227C05","layers":[{"animations":[],"initialState":{"affineTransform":[1,0,0,1,0,0],"masksToBounds":false,"rotation":0,"scale":1,"position":{"pointX":15.699999999999932,"pointY":363.39999999999998},"width":34,"sublayerTransform":[1,0,0,0,0,1,0,0,0,0,1,-0.00035007912466775983,0,0,0,1],"contentsRect":{"y":0,"x":0,"width":1,"height":1},"opacity":1,"edgeAntialiasingMask":251658240,"height":124,"hidden":false,"anchorPoint":{"pointX":0.46176470588235091,"pointY":2.9306451612903226}},"layers":[{"animations":[{"timeOffset":0,"beginTime":1e-100,"repeatCount":0,"animations":[{"timeOffset":0,"from":{"scalar":0},"beginTime":0,"repeatCount":0,"fillMode":"both","duration":0.29999999999999999,"autoreverses":false,"timingFunction":"EaseInEaseOut","property":"opacity","to":{"scalar":1}},{"timeOffset":0,"from":{"scalar":false},"beginTime":0,"repeatCount":0,"fillMode":"forwards","property":"hidden","autoreverses":false,"duration":0.29999999999999999,"to":{"scalar":false}}],"fillMode":"both","autoreverses":false,"duration":0.29999999999999999}],"layers":[],"texturedRectangle":{"singleTextureOpacity":1,"textXHeight":0,"shapePath":{"lineWidth":1,"flatness":0.59999999999999998,"lineCapStyle":0,"elements":[{"type":"MoveToPoint","points":[[16.900000000000091,1.6000000000000227]]},{"type":"AddLine","points":[[16.900000000000091,91.700000000000045]]},{"type":"AddLine","points":[[16.900000000000091,95.700000000000045]]}],"windingRule":0,"lineJoinStyle":0,"miterLimit":10},"isBackgroundTexture":true,"textBaseline":0,"isVerticalText":false,"textureType":5},"initialState":{"affineTransform":[1,0,0,1,0,0],"masksToBounds":false,"rotation":0,"scale":1,"position":{"pointX":15.699999999999932,"pointY":60.399999999999977},"width":34,"sublayerTransform":[1,0,0,0,0,1,0,0,0,0,1,0,0,0,0,1],"contentsRect":{"y":0,"x":0,"width":1,"height":1},"opacity":1,"edgeAntialiasingMask":0,"height":124,"hidden":true,"anchorPoint":{"pointX":0.5,"pointY":0.5}},"texture":"0FEF2B786609238E24DCBD6FA003DA71"}]}]},"effects":[],"duration":0.29999999999999999,"type":"buildIn","name":"apple:dissolve character","objectID":"B40CEB66-27F9-4E74-BF73-EE1640227C05"},{"beginTime":0,"baseLayer":{"animations":[],"initialState":{"affineTransform":[1,0,0,1,0,0],"masksToBounds":false,"rotation":0,"scale":1,"position":{"pointX":746,"pointY":494.70000000000005},"width":441,"sublayerTransform":[1,0,0,0,0,1,0,0,0,0,1,0,0,0,0,1],"contentsRect":{"y":0,"x":0,"width":1,"height":1},"opacity":1,"edgeAntialiasingMask":251658240,"height":143,"hidden":false,"anchorPoint":{"pointX":0.5,"pointY":0.5}},"objectID":"D50B8826-71B6-4A0D-9E46-08E58B3CC3F7","layers":[{"animations":[],"initialState":{"affineTransform":[1,0,0,1,0,0],"masksToBounds":false,"rotation":0,"scale":1,"position":{"pointX":434.5,"pointY":116.79999999999995},"width":441,"sublayerTransform":[1,0,0,0,0,1,0,0,0,0,1,-0.00035007912466775983,0,0,0,1],"contentsRect":{"y":0,"x":0,"width":1,"height":1},"opacity":1,"edgeAntialiasingMask":251658240,"height":143,"hidden":false,"anchorPoint":{"pointX":0.98526077097505671,"pointY":0.81678321678321641}},"layers":[{"animations":[{"timeOffset":0,"beginTime":1e-100,"repeatCount":0,"animations":[{"timeOffset":0,"from":{"scalar":0},"beginTime":0,"repeatCount":0,"fillMode":"both","duration":0.29999999999999999,"autoreverses":false,"timingFunction":"EaseInEaseOut","property":"opacity","to":{"scalar":1}},{"timeOffset":0,"from":{"scalar":false},"beginTime":0,"repeatCount":0,"fillMode":"forwards","property":"hidden","autoreverses":false,"duration":0.29999999999999999,"to":{"scalar":false}}],"fillMode":"both","autoreverses":false,"duration":0.29999999999999999}],"layers":[],"texturedRectangle":{"singleTextureOpacity":1,"textXHeight":0,"shapePath":{"lineWidth":1,"flatness":0.59999999999999998,"lineCapStyle":0,"elements":[{"type":"MoveToPoint","points":[[435.90000000000009,1.2000000000000455]]},{"type":"AddLine","points":[[435.90000000000009,68.100000000000023]]},{"type":"AddLine","points":[[17.100000000000023,68.100000000000023]]},{"type":"AddLine","points":[[17.100000000000023,109.89999999999998]]},{"type":"AddLine","points":[[17.100000000000023,113.89999999999998]]}],"windingRule":0,"lineJoinStyle":0,"miterLimit":10},"isBackgroundTexture":true,"textBaseline":0,"isVerticalText":false,"textureType":5},"initialState":{"affineTransform":[1,0,0,1,0,0],"masksToBounds":false,"rotation":0,"scale":1,"position":{"pointX":219,"pointY":70.299999999999955},"width":441,"sublayerTransform":[1,0,0,0,0,1,0,0,0,0,1,0,0,0,0,1],"contentsRect":{"y":0,"x":0,"width":1,"height":1},"opacity":1,"edgeAntialiasingMask":0,"height":143,"hidden":true,"anchorPoint":{"pointX":0.5,"pointY":0.5}},"texture":"9211CEF4A32EFCE19DDE0CF9CF6F5DB5"}]}]},"effects":[],"duration":0.29999999999999999,"type":"buildIn","name":"apple:dissolve character","objectID":"D50B8826-71B6-4A0D-9E46-08E58B3CC3F7"},{"beginTime":0,"baseLayer":{"animations":[],"initialState":{"affineTransform":[1,0,0,1,0,0],"masksToBounds":false,"rotation":0,"scale":1,"position":{"pointX":1176.9000000000001,"pointY":494.70000000000005},"width":442,"sublayerTransform":[1,0,0,0,0,1,0,0,0,0,1,0,0,0,0,1],"contentsRect":{"y":0,"x":0,"width":1,"height":1},"opacity":1,"edgeAntialiasingMask":251658240,"height":143,"hidden":false,"anchorPoint":{"pointX":0.5,"pointY":0.5}},"objectID":"DD1B31DF-6619-4B5D-8A79-8C6F30D76B17","layers":[{"animations":[],"initialState":{"affineTransform":[1,0,0,1,0,0],"masksToBounds":false,"rotation":0,"scale":1,"position":{"pointX":4.0999999999999091,"pointY":116.79999999999995},"width":442,"sublayerTransform":[1,0,0,0,0,1,0,0,0,0,1,-0.00035007912466775983,0,0,0,1],"contentsRect":{"y":0,"x":0,"width":1,"height":1},"opacity":1,"edgeAntialiasingMask":251658240,"height":143,"hidden":false,"anchorPoint":{"pointX":0.0092760180995473049,"pointY":0.81678321678321641}},"layers":[{"animations":[{"timeOffset":0,"beginTime":1e-100,"repeatCount":0,"animations":[{"timeOffset":0,"from":{"scalar":0},"beginTime":0,"repeatCount":0,"fillMode":"both","duration":0.29999999999999999,"autoreverses":false,"timingFunction":"EaseInEaseOut","property":"opacity","to":{"scalar":1}},{"timeOffset":0,"from":{"scalar":false},"beginTime":0,"repeatCount":0,"fillMode":"forwards","property":"hidden","autoreverses":false,"duration":0.29999999999999999,"to":{"scalar":false}}],"fillMode":"both","autoreverses":false,"duration":0.29999999999999999}],"layers":[],"texturedRectangle":{"singleTextureOpacity":1,"textXHeight":0,"shapePath":{"lineWidth":1,"flatness":0.59999999999999998,"lineCapStyle":0,"elements":[{"type":"MoveToPoint","points":[[5.9000000000000909,1.2000000000000455]]},{"type":"AddLine","points":[[5.9000000000000909,68.100000000000023]]},{"type":"AddLine","points":[[424.80000000000018,68.100000000000023]]},{"type":"AddLine","points":[[424.80000000000018,109.89999999999998]]},{"type":"AddLine","points":[[424.80000000000018,113.89999999999998]]}],"windingRule":0,"lineJoinStyle":0,"miterLimit":10},"isBackgroundTexture":true,"textBaseline":0,"isVerticalText":false,"textureType":5},"initialState":{"affineTransform":[1,0,0,1,0,0],"masksToBounds":false,"rotation":0,"scale":1,"position":{"pointX":219.09999999999991,"pointY":70.299999999999955},"width":442,"sublayerTransform":[1,0,0,0,0,1,0,0,0,0,1,0,0,0,0,1],"contentsRect":{"y":0,"x":0,"width":1,"height":1},"opacity":1,"edgeAntialiasingMask":0,"height":143,"hidden":true,"anchorPoint":{"pointX":0.5,"pointY":0.5}},"texture":"08F420D27E33D0EC9CABBBFB1CBFCF70"}]}]},"effects":[],"duration":0.29999999999999999,"type":"buildIn","name":"apple:dissolve character","objectID":"DD1B31DF-6619-4B5D-8A79-8C6F30D76B17"},{"beginTime":0,"baseLayer":{"animations":[],"initialState":{"affineTransform":[1,0,0,1,0,0],"masksToBounds":false,"rotation":0,"scale":1,"position":{"pointX":1380.2000000000003,"pointY":759.90000000000009},"width":34,"sublayerTransform":[1,0,0,0,0,1,0,0,0,0,1,0,0,0,0,1],"contentsRect":{"y":0,"x":0,"width":1,"height":1},"opacity":1,"edgeAntialiasingMask":251658240,"height":143,"hidden":false,"anchorPoint":{"pointX":0.5,"pointY":0.5}},"objectID":"71C7034D-C2C2-41A7-8910-3A95DFFF9E37","layers":[{"animations":[],"initialState":{"affineTransform":[1,0,0,1,0,0],"masksToBounds":false,"rotation":0,"scale":1,"position":{"pointX":-403.20000000000027,"pointY":-148.40000000000009},"width":34,"sublayerTransform":[1,0,0,0,0,1,0,0,0,0,1,-0.00035007912466775983,0,0,0,1],"contentsRect":{"y":0,"x":0,"width":1,"height":1},"opacity":1,"edgeAntialiasingMask":251658240,"height":143,"hidden":false,"anchorPoint":{"pointX":-11.858823529411772,"pointY":-1.0377622377622384}},"layers":[{"animations":[{"timeOffset":0,"beginTime":1e-100,"repeatCount":0,"animations":[{"timeOffset":0,"from":{"scalar":0},"beginTime":0,"repeatCount":0,"fillMode":"both","duration":0.29999999999999999,"autoreverses":false,"timingFunction":"EaseInEaseOut","property":"opacity","to":{"scalar":1}},{"timeOffset":0,"from":{"scalar":false},"beginTime":0,"repeatCount":0,"fillMode":"forwards","property":"hidden","autoreverses":false,"duration":0.29999999999999999,"to":{"scalar":false}}],"fillMode":"both","autoreverses":false,"duration":0.29999999999999999}],"layers":[],"texturedRectangle":{"singleTextureOpacity":1,"textXHeight":0,"shapePath":{"lineWidth":1,"flatness":0.59999999999999998,"lineCapStyle":0,"elements":[{"type":"MoveToPoint","points":[[16.800000000000182,1.4000000000000909]]},{"type":"AddLine","points":[[16.800000000000182,110.20000000000005]]},{"type":"AddLine","points":[[16.800000000000182,114.20000000000005]]}],"windingRule":0,"lineJoinStyle":0,"miterLimit":10},"isBackgroundTexture":true,"textBaseline":0,"isVerticalText":false,"textureType":5},"initialState":{"affineTransform":[1,0,0,1,0,0],"masksToBounds":false,"rotation":0,"scale":1,"position":{"pointX":15.799999999999727,"pointY":70.099999999999909},"width":34,"sublayerTransform":[1,0,0,0,0,1,0,0,0,0,1,0,0,0,0,1],"contentsRect":{"y":0,"x":0,"width":1,"height":1},"opacity":1,"edgeAntialiasingMask":0,"height":143,"hidden":true,"anchorPoint":{"pointX":0.5,"pointY":0.5}},"texture":"C2A54592E8BA3E35D010F868277412E0"}]}]},"effects":[],"duration":0.29999999999999999,"type":"buildIn","name":"apple:dissolve character","objectID":"71C7034D-C2C2-41A7-8910-3A95DFFF9E37"}],"automaticPlay":false,"hyperlinks":[],"accessibility":[{"text":"<search-movies-box\/>","targetRectangle":{"y":601.19805908203125,"x":319.39675903320312,"width":443.54296875,"height":50}},{"text":"<movies-list\/>","targetRectangle":{"y":601.19805908203125,"x":1238.7633972167969,"width":280.13671875,"height":50}},{"text":"<movies-list-item\/>","targetRectangle":{"y":866.4183349609375,"x":1188.5910339355469,"width":380.4814453125,"height":50}},{"text":"<search-movies-page\/>","targetRectangle":{"y":335.97772216796875,"x":726.54928588867188,"width":466.9013671875,"height":50}},{"text":"outside world","targetRectangle":{"y":57.746328443288803,"x":761.20310890674591,"width":397.59375,"height":61.5703125}}],"baseLayer":{"animations":[],"initialState":{"affineTransform":[1,0,0,1,0,0],"masksToBounds":false,"rotation":0,"scale":1,"position":{"pointX":960,"pointY":540},"width":1920,"sublayerTransform":[1,0,0,0,0,1,0,0,0,0,1,0,0,0,0,1],"contentsRect":{"y":0,"x":0,"width":1,"height":1},"opacity":1,"edgeAntialiasingMask":251658240,"height":1080,"hidden":false,"anchorPoint":{"pointX":0.5,"pointY":0.5}},"layers":[{"animations":[],"initialState":{"affineTransform":[1,0,0,1,0,0],"masksToBounds":false,"rotation":0,"scale":1,"position":{"pointX":960,"pointY":540},"width":1920,"sublayerTransform":[1,0,0,0,0,1,0,0,0,0,1,0,0,0,0,1],"contentsRect":{"y":0,"x":0,"width":1,"height":1},"opacity":1,"edgeAntialiasingMask":251658240,"height":1080,"hidden":false,"anchorPoint":{"pointX":0.5,"pointY":0.5}},"layers":[{"animations":[],"initialState":{"affineTransform":[1,0,0,1,0,0],"masksToBounds":false,"rotation":0,"scale":1,"position":{"pointX":960,"pointY":540},"width":1920,"sublayerTransform":[1,0,0,0,0,1,0,0,0,0,1,0,0,0,0,1],"contentsRect":{"y":0,"x":0,"width":1,"height":1},"opacity":1,"edgeAntialiasingMask":251658240,"height":1080,"hidden":false,"anchorPoint":{"pointX":0.5,"pointY":0.5}},"layers":[{"animations":[],"layers":[],"texturedRectangle":{"isBackgroundTexture":true,"singleTextureOpacity":1,"textureType":1,"textBaseline":0,"textXHeight":0,"isVerticalText":false},"initialState":{"affineTransform":[1,0,0,1,0,0],"masksToBounds":false,"rotation":0,"scale":1,"position":{"pointX":960,"pointY":540},"width":1920,"sublayerTransform":[1,0,0,0,0,1,0,0,0,0,1,0,0,0,0,1],"contentsRect":{"y":0,"x":0,"width":1,"height":1},"opacity":1,"edgeAntialiasingMask":0,"height":1080,"hidden":false,"anchorPoint":{"pointX":0.5,"pointY":0.5}},"texture":"63320DF3585E5970F64F12FDA3FAB4CB"}]}]},{"animations":[],"initialState":{"affineTransform":[1,0,0,1,0,0],"masksToBounds":false,"rotation":0,"scale":1,"position":{"pointX":960,"pointY":540},"width":1920,"sublayerTransform":[1,0,0,0,0,1,0,0,0,0,1,0,0,0,0,1],"contentsRect":{"y":0,"x":0,"width":1,"height":1},"opacity":1,"edgeAntialiasingMask":251658240,"height":1080,"hidden":false,"anchorPoint":{"pointX":0.5,"pointY":0.5}},"layers":[{"animations":[],"initialState":{"affineTransform":[1,0,0,1,0,0],"masksToBounds":false,"rotation":0,"scale":1,"position":{"pointX":961.33447265625,"pointY":362.47772216796875},"width":620,"sublayerTransform":[1,0,0,0,0,1,0,0,0,0,1,0,0,0,0,1],"contentsRect":{"y":0,"x":0,"width":1,"height":1},"opacity":1,"edgeAntialiasingMask":251658240,"height":129,"hidden":false,"anchorPoint":{"pointX":0.5,"pointY":0.5}},"layers":[{"animations":[],"layers":[],"texturedRectangle":{"singleTextureOpacity":1,"textXHeight":0,"shapePath":{"lineWidth":1,"flatness":0.59999999999999998,"lineCapStyle":0,"elements":[{"type":"MoveToPoint","points":[[5.33447265625,5.97772216796875]]},{"type":"AddLine","points":[[614.66546630859375,5.97772216796875]]},{"type":"AddLine","points":[[614.66546630859375,123.26389312744141]]},{"type":"AddLine","points":[[5.33447265625,123.26389312744141]]},{"type":"CloseSubpath"},{"type":"MoveToPoint","points":[[5.33447265625,5.97772216796875]]}],"windingRule":0,"lineJoinStyle":0,"miterLimit":10},"isBackgroundTexture":true,"textBaseline":0,"isVerticalText":false,"textureType":5},"initialState":{"affineTransform":[1,0,0,1,0,0],"masksToBounds":false,"rotation":0,"scale":1,"position":{"pointX":308.66552734375,"pointY":62.52227783203125},"width":620,"sublayerTransform":[1,0,0,0,0,1,0,0,0,0,1,0,0,0,0,1],"contentsRect":{"y":0,"x":0,"width":1,"height":1},"opacity":1,"edgeAntialiasingMask":0,"height":129,"hidden":false,"anchorPoint":{"pointX":0.5,"pointY":0.5}},"texture":"00EF00B3FF14D579613EFF71EF05F5D2"}]}]},{"animations":[],"initialState":{"affineTransform":[1,0,0,1,0,0],"masksToBounds":false,"rotation":0,"scale":1,"position":{"pointX":960,"pointY":540},"width":1920,"sublayerTransform":[1,0,0,0,0,1,0,0,0,0,1,0,0,0,0,1],"contentsRect":{"y":0,"x":0,"width":1,"height":1},"opacity":1,"edgeAntialiasingMask":251658240,"height":1080,"hidden":false,"anchorPoint":{"pointX":0.5,"pointY":0.5}},"layers":[{"animations":[],"initialState":{"affineTransform":[1,0,0,1,0,0],"masksToBounds":false,"rotation":0,"scale":1,"position":{"pointX":542.50274658203125,"pointY":627.19805908203125},"width":620,"sublayerTransform":[1,0,0,0,0,1,0,0,0,0,1,0,0,0,0,1],"contentsRect":{"y":0,"x":0,"width":1,"height":1},"opacity":1,"edgeAntialiasingMask":251658240,"height":128,"hidden":false,"anchorPoint":{"pointX":0.5,"pointY":0.5}},"layers":[{"animations":[],"layers":[],"texturedRectangle":{"singleTextureOpacity":1,"textXHeight":0,"shapePath":{"lineWidth":1,"flatness":0.59999999999999998,"lineCapStyle":0,"elements":[{"type":"MoveToPoint","points":[[5.50274658203125,5.19805908203125]]},{"type":"AddLine","points":[[614.833740234375,5.19805908203125]]},{"type":"AddLine","points":[[614.833740234375,122.48423004150391]]},{"type":"AddLine","points":[[5.50274658203125,122.48423004150391]]},{"type":"CloseSubpath"},{"type":"MoveToPoint","points":[[5.50274658203125,5.19805908203125]]}],"windingRule":0,"lineJoinStyle":0,"miterLimit":10},"isBackgroundTexture":true,"textBaseline":0,"isVerticalText":false,"textureType":5},"initialState":{"affineTransform":[1,0,0,1,0,0],"masksToBounds":false,"rotation":0,"scale":1,"position":{"pointX":308.49725341796875,"pointY":62.80194091796875},"width":620,"sublayerTransform":[1,0,0,0,0,1,0,0,0,0,1,0,0,0,0,1],"contentsRect":{"y":0,"x":0,"width":1,"height":1},"opacity":1,"edgeAntialiasingMask":0,"height":128,"hidden":false,"anchorPoint":{"pointX":0.5,"pointY":0.5}},"texture":"453BE8B0F2DA81A5A63782E720315E21"}]}]},{"animations":[],"initialState":{"affineTransform":[1,0,0,1,0,0],"masksToBounds":false,"rotation":0,"scale":1,"position":{"pointX":960,"pointY":540},"width":1920,"sublayerTransform":[1,0,0,0,0,1,0,0,0,0,1,0,0,0,0,1],"contentsRect":{"y":0,"x":0,"width":1,"height":1},"opacity":1,"edgeAntialiasingMask":251658240,"height":1080,"hidden":false,"anchorPoint":{"pointX":0.5,"pointY":0.5}},"layers":[{"animations":[],"initialState":{"affineTransform":[1,0,0,1,0,0],"masksToBounds":false,"rotation":0,"scale":1,"position":{"pointX":1380.166259765625,"pointY":627.19805908203125},"width":620,"sublayerTransform":[1,0,0,0,0,1,0,0,0,0,1,0,0,0,0,1],"contentsRect":{"y":0,"x":0,"width":1,"height":1},"opacity":1,"edgeAntialiasingMask":251658240,"height":128,"hidden":false,"anchorPoint":{"pointX":0.5,"pointY":0.5}},"layers":[{"animations":[],"layers":[],"texturedRectangle":{"singleTextureOpacity":1,"textXHeight":0,"shapePath":{"lineWidth":1,"flatness":0.59999999999999998,"lineCapStyle":0,"elements":[{"type":"MoveToPoint","points":[[5.166259765625,5.19805908203125]]},{"type":"AddLine","points":[[614.49725341796875,5.19805908203125]]},{"type":"AddLine","points":[[614.49725341796875,122.48423004150391]]},{"type":"AddLine","points":[[5.166259765625,122.48423004150391]]},{"type":"CloseSubpath"},{"type":"MoveToPoint","points":[[5.166259765625,5.19805908203125]]}],"windingRule":0,"lineJoinStyle":0,"miterLimit":10},"isBackgroundTexture":true,"textBaseline":0,"isVerticalText":false,"textureType":5},"initialState":{"affineTransform":[1,0,0,1,0,0],"masksToBounds":false,"rotation":0,"scale":1,"position":{"pointX":308.833740234375,"pointY":62.80194091796875},"width":620,"sublayerTransform":[1,0,0,0,0,1,0,0,0,0,1,0,0,0,0,1],"contentsRect":{"y":0,"x":0,"width":1,"height":1},"opacity":1,"edgeAntialiasingMask":0,"height":128,"hidden":false,"anchorPoint":{"pointX":0.5,"pointY":0.5}},"texture":"599DC56368438AE14825012FB21F2616"}]}]},{"animations":[],"initialState":{"affineTransform":[1,0,0,1,0,0],"masksToBounds":false,"rotation":0,"scale":1,"position":{"pointX":960,"pointY":540},"width":1920,"sublayerTransform":[1,0,0,0,0,1,0,0,0,0,1,0,0,0,0,1],"contentsRect":{"y":0,"x":0,"width":1,"height":1},"opacity":1,"edgeAntialiasingMask":251658240,"height":1080,"hidden":false,"anchorPoint":{"pointX":0.5,"pointY":0.5}},"layers":[{"animations":[],"initialState":{"affineTransform":[1,0,0,1,0,0],"masksToBounds":false,"rotation":0,"scale":1,"position":{"pointX":1380.166259765625,"pointY":892.4183349609375},"width":620,"sublayerTransform":[1,0,0,0,0,1,0,0,0,0,1,0,0,0,0,1],"contentsRect":{"y":0,"x":0,"width":1,"height":1},"opacity":1,"edgeAntialiasingMask":251658240,"height":128,"hidden":false,"anchorPoint":{"pointX":0.5,"pointY":0.5}},"layers":[{"animations":[],"layers":[],"texturedRectangle":{"singleTextureOpacity":1,"textXHeight":0,"shapePath":{"lineWidth":1,"flatness":0.59999999999999998,"lineCapStyle":0,"elements":[{"type":"MoveToPoint","points":[[5.166259765625,5.4183349609375]]},{"type":"AddLine","points":[[614.49725341796875,5.4183349609375]]},{"type":"AddLine","points":[[614.49725341796875,122.70450592041016]]},{"type":"AddLine","points":[[5.166259765625,122.70450592041016]]},{"type":"CloseSubpath"},{"type":"MoveToPoint","points":[[5.166259765625,5.4183349609375]]}],"windingRule":0,"lineJoinStyle":0,"miterLimit":10},"isBackgroundTexture":true,"textBaseline":0,"isVerticalText":false,"textureType":5},"initialState":{"affineTransform":[1,0,0,1,0,0],"masksToBounds":false,"rotation":0,"scale":1,"position":{"pointX":308.833740234375,"pointY":62.5816650390625},"width":620,"sublayerTransform":[1,0,0,0,0,1,0,0,0,0,1,0,0,0,0,1],"contentsRect":{"y":0,"x":0,"width":1,"height":1},"opacity":1,"edgeAntialiasingMask":0,"height":128,"hidden":false,"anchorPoint":{"pointX":0.5,"pointY":0.5}},"texture":"C9F81E9FC932E0891783B87EDE7E3B6E"}]}]},{"animations":[],"initialState":{"affineTransform":[1,0,0,1,0,0],"masksToBounds":false,"rotation":0,"scale":1,"position":{"pointX":960,"pointY":540},"width":1920,"sublayerTransform":[1,0,0,0,0,1,0,0,0,0,1,0,0,0,0,1],"contentsRect":{"y":0,"x":0,"width":1,"height":1},"opacity":1,"edgeAntialiasingMask":251658240,"height":1080,"hidden":false,"anchorPoint":{"pointX":0.5,"pointY":0.5}},"layers":[{"animations":[],"initialState":{"affineTransform":[1,0,0,1,0,0],"masksToBounds":false,"rotation":0,"scale":1,"position":{"pointX":961.70493996143341,"pointY":89.746328443288803},"width":1926,"sublayerTransform":[1,0,0,0,0,1,0,0,0,0,1,0,0,0,0,1],"contentsRect":{"y":0,"x":0,"width":1,"height":1},"opacity":1,"edgeAntialiasingMask":251658240,"height":180,"hidden":false,"anchorPoint":{"pointX":0.5,"pointY":0.5}},"layers":[{"animations":[],"layers":[],"texturedRectangle":{"singleTextureOpacity":1,"textXHeight":0,"shapePath":{"lineWidth":1,"flatness":0.59999999999999998,"lineCapStyle":0,"elements":[{"type":"MoveToPoint","points":[[1.7049399614334106,1.7463284432888031]]},{"type":"AddLine","points":[[1924.2950278520584,1.7463284432888031]]},{"type":"AddLine","points":[[1924.2950278520584,178.65262421965599]]},{"type":"AddLine","points":[[1.7049399614334106,178.65262421965599]]},{"type":"CloseSubpath"},{"type":"MoveToPoint","points":[[1.7049399614334106,1.7463284432888031]]}],"windingRule":0,"lineJoinStyle":0,"miterLimit":10},"isBackgroundTexture":true,"textBaseline":0,"isVerticalText":false,"textureType":5},"initialState":{"affineTransform":[1,0,0,1,0,0],"masksToBounds":false,"rotation":0,"scale":1,"position":{"pointX":961.29506003856659,"pointY":88.253671556711197},"width":1926,"sublayerTransform":[1,0,0,0,0,1,0,0,0,0,1,0,0,0,0,1],"contentsRect":{"y":0,"x":0,"width":1,"height":1},"opacity":1,"edgeAntialiasingMask":0,"height":180,"hidden":false,"anchorPoint":{"pointX":0.5,"pointY":0.5}},"texture":"5299F162DC250DDCFDCD2A19147CC01B"}]}]},{"animations":[],"initialState":{"affineTransform":[1,0,0,1,0,0],"masksToBounds":false,"rotation":0,"scale":1,"position":{"pointX":960,"pointY":540},"width":1920,"sublayerTransform":[1,0,0,0,0,1,0,0,0,0,1,0,0,0,0,1],"contentsRect":{"y":0,"x":0,"width":1,"height":1},"opacity":1,"edgeAntialiasingMask":251658240,"height":1080,"hidden":false,"anchorPoint":{"pointX":0.5,"pointY":0.5}},"layers":[{"animations":[],"initialState":{"affineTransform":[1,0,0,1,0,0],"masksToBounds":false,"rotation":0,"scale":1,"position":{"pointX":961.30000000000007,"pointY":238.60000000000002},"width":34,"sublayerTransform":[1,0,0,0,0,1,0,0,0,0,1,0,0,0,0,1],"contentsRect":{"y":0,"x":0,"width":1,"height":1},"opacity":1,"edgeAntialiasingMask":251658240,"height":124,"hidden":false,"anchorPoint":{"pointX":0.5,"pointY":0.5}},"objectID":"B40CEB66-27F9-4E74-BF73-EE1640227C05","layers":[{"animations":[],"layers":[],"texturedRectangle":{"singleTextureOpacity":1,"textXHeight":0,"shapePath":{"lineWidth":1,"flatness":0.59999999999999998,"lineCapStyle":0,"elements":[{"type":"MoveToPoint","points":[[16.900000000000091,1.6000000000000227]]},{"type":"AddLine","points":[[16.900000000000091,91.700000000000045]]},{"type":"AddLine","points":[[16.900000000000091,95.700000000000045]]}],"windingRule":0,"lineJoinStyle":0,"miterLimit":10},"isBackgroundTexture":true,"textBaseline":0,"isVerticalText":false,"textureType":5},"initialState":{"affineTransform":[1,0,0,1,0,0],"masksToBounds":false,"rotation":0,"scale":1,"position":{"pointX":15.699999999999932,"pointY":60.399999999999977},"width":34,"sublayerTransform":[1,0,0,0,0,1,0,0,0,0,1,0,0,0,0,1],"contentsRect":{"y":0,"x":0,"width":1,"height":1},"opacity":1,"edgeAntialiasingMask":0,"height":124,"hidden":true,"anchorPoint":{"pointX":0.5,"pointY":0.5}},"texture":"0FEF2B786609238E24DCBD6FA003DA71"}]}]},{"animations":[],"initialState":{"affineTransform":[1,0,0,1,0,0],"masksToBounds":false,"rotation":0,"scale":1,"position":{"pointX":960,"pointY":540},"width":1920,"sublayerTransform":[1,0,0,0,0,1,0,0,0,0,1,0,0,0,0,1],"contentsRect":{"y":0,"x":0,"width":1,"height":1},"opacity":1,"edgeAntialiasingMask":251658240,"height":1080,"hidden":false,"anchorPoint":{"pointX":0.5,"pointY":0.5}},"layers":[{"animations":[],"initialState":{"affineTransform":[1,0,0,1,0,0],"masksToBounds":false,"rotation":0,"scale":1,"position":{"pointX":746,"pointY":494.70000000000005},"width":441,"sublayerTransform":[1,0,0,0,0,1,0,0,0,0,1,0,0,0,0,1],"contentsRect":{"y":0,"x":0,"width":1,"height":1},"opacity":1,"edgeAntialiasingMask":251658240,"height":143,"hidden":false,"anchorPoint":{"pointX":0.5,"pointY":0.5}},"objectID":"D50B8826-71B6-4A0D-9E46-08E58B3CC3F7","layers":[{"animations":[],"layers":[],"texturedRectangle":{"singleTextureOpacity":1,"textXHeight":0,"shapePath":{"lineWidth":1,"flatness":0.59999999999999998,"lineCapStyle":0,"elements":[{"type":"MoveToPoint","points":[[435.90000000000009,1.2000000000000455]]},{"type":"AddLine","points":[[435.90000000000009,68.100000000000023]]},{"type":"AddLine","points":[[17.100000000000023,68.100000000000023]]},{"type":"AddLine","points":[[17.100000000000023,109.89999999999998]]},{"type":"AddLine","points":[[17.100000000000023,113.89999999999998]]}],"windingRule":0,"lineJoinStyle":0,"miterLimit":10},"isBackgroundTexture":true,"textBaseline":0,"isVerticalText":false,"textureType":5},"initialState":{"affineTransform":[1,0,0,1,0,0],"masksToBounds":false,"rotation":0,"scale":1,"position":{"pointX":219,"pointY":70.299999999999955},"width":441,"sublayerTransform":[1,0,0,0,0,1,0,0,0,0,1,0,0,0,0,1],"contentsRect":{"y":0,"x":0,"width":1,"height":1},"opacity":1,"edgeAntialiasingMask":0,"height":143,"hidden":true,"anchorPoint":{"pointX":0.5,"pointY":0.5}},"texture":"9211CEF4A32EFCE19DDE0CF9CF6F5DB5"}]}]},{"animations":[],"initialState":{"affineTransform":[1,0,0,1,0,0],"masksToBounds":false,"rotation":0,"scale":1,"position":{"pointX":960,"pointY":540},"width":1920,"sublayerTransform":[1,0,0,0,0,1,0,0,0,0,1,0,0,0,0,1],"contentsRect":{"y":0,"x":0,"width":1,"height":1},"opacity":1,"edgeAntialiasingMask":251658240,"height":1080,"hidden":false,"anchorPoint":{"pointX":0.5,"pointY":0.5}},"layers":[{"animations":[],"initialState":{"affineTransform":[1,0,0,1,0,0],"masksToBounds":false,"rotation":0,"scale":1,"position":{"pointX":1176.9000000000001,"pointY":494.70000000000005},"width":442,"sublayerTransform":[1,0,0,0,0,1,0,0,0,0,1,0,0,0,0,1],"contentsRect":{"y":0,"x":0,"width":1,"height":1},"opacity":1,"edgeAntialiasingMask":251658240,"height":143,"hidden":false,"anchorPoint":{"pointX":0.5,"pointY":0.5}},"objectID":"DD1B31DF-6619-4B5D-8A79-8C6F30D76B17","layers":[{"animations":[],"layers":[],"texturedRectangle":{"singleTextureOpacity":1,"textXHeight":0,"shapePath":{"lineWidth":1,"flatness":0.59999999999999998,"lineCapStyle":0,"elements":[{"type":"MoveToPoint","points":[[5.9000000000000909,1.2000000000000455]]},{"type":"AddLine","points":[[5.9000000000000909,68.100000000000023]]},{"type":"AddLine","points":[[424.80000000000018,68.100000000000023]]},{"type":"AddLine","points":[[424.80000000000018,109.89999999999998]]},{"type":"AddLine","points":[[424.80000000000018,113.89999999999998]]}],"windingRule":0,"lineJoinStyle":0,"miterLimit":10},"isBackgroundTexture":true,"textBaseline":0,"isVerticalText":false,"textureType":5},"initialState":{"affineTransform":[1,0,0,1,0,0],"masksToBounds":false,"rotation":0,"scale":1,"position":{"pointX":219.09999999999991,"pointY":70.299999999999955},"width":442,"sublayerTransform":[1,0,0,0,0,1,0,0,0,0,1,0,0,0,0,1],"contentsRect":{"y":0,"x":0,"width":1,"height":1},"opacity":1,"edgeAntialiasingMask":0,"height":143,"hidden":true,"anchorPoint":{"pointX":0.5,"pointY":0.5}},"texture":"08F420D27E33D0EC9CABBBFB1CBFCF70"}]}]},{"animations":[],"initialState":{"affineTransform":[1,0,0,1,0,0],"masksToBounds":false,"rotation":0,"scale":1,"position":{"pointX":960,"pointY":540},"width":1920,"sublayerTransform":[1,0,0,0,0,1,0,0,0,0,1,0,0,0,0,1],"contentsRect":{"y":0,"x":0,"width":1,"height":1},"opacity":1,"edgeAntialiasingMask":251658240,"height":1080,"hidden":false,"anchorPoint":{"pointX":0.5,"pointY":0.5}},"layers":[{"animations":[],"initialState":{"affineTransform":[1,0,0,1,0,0],"masksToBounds":false,"rotation":0,"scale":1,"position":{"pointX":1380.2000000000003,"pointY":759.90000000000009},"width":34,"sublayerTransform":[1,0,0,0,0,1,0,0,0,0,1,0,0,0,0,1],"contentsRect":{"y":0,"x":0,"width":1,"height":1},"opacity":1,"edgeAntialiasingMask":251658240,"height":143,"hidden":false,"anchorPoint":{"pointX":0.5,"pointY":0.5}},"objectID":"71C7034D-C2C2-41A7-8910-3A95DFFF9E37","layers":[{"animations":[],"layers":[],"texturedRectangle":{"singleTextureOpacity":1,"textXHeight":0,"shapePath":{"lineWidth":1,"flatness":0.59999999999999998,"lineCapStyle":0,"elements":[{"type":"MoveToPoint","points":[[16.800000000000182,1.4000000000000909]]},{"type":"AddLine","points":[[16.800000000000182,110.20000000000005]]},{"type":"AddLine","points":[[16.800000000000182,114.20000000000005]]}],"windingRule":0,"lineJoinStyle":0,"miterLimit":10},"isBackgroundTexture":true,"textBaseline":0,"isVerticalText":false,"textureType":5},"initialState":{"affineTransform":[1,0,0,1,0,0],"masksToBounds":false,"rotation":0,"scale":1,"position":{"pointX":15.799999999999727,"pointY":70.099999999999909},"width":34,"sublayerTransform":[1,0,0,0,0,1,0,0,0,0,1,0,0,0,0,1],"contentsRect":{"y":0,"x":0,"width":1,"height":1},"opacity":1,"edgeAntialiasingMask":0,"height":143,"hidden":true,"anchorPoint":{"pointX":0.5,"pointY":0.5}},"texture":"C2A54592E8BA3E35D010F868277412E0"}]}]},{"animations":[],"initialState":{"affineTransform":[1,0,0,1,0,0],"masksToBounds":false,"rotation":0,"scale":1,"position":{"pointX":960,"pointY":540},"width":1920,"sublayerTransform":[1,0,0,0,0,1,0,0,0,0,1,0,0,0,0,1],"contentsRect":{"y":0,"x":0,"width":1,"height":1},"opacity":1,"edgeAntialiasingMask":251658240,"height":1080,"hidden":false,"anchorPoint":{"pointX":0.5,"pointY":0.5}},"layers":[{"animations":[],"initialState":{"affineTransform":[1,0,0,1,0,0],"masksToBounds":false,"rotation":0,"scale":1,"position":{"pointX":961.30000000000007,"pointY":238.60000000000002},"width":34,"sublayerTransform":[1,0,0,0,0,1,0,0,0,0,1,0,0,0,0,1],"contentsRect":{"y":0,"x":0,"width":1,"height":1},"opacity":1,"edgeAntialiasingMask":251658240,"height":124,"hidden":false,"anchorPoint":{"pointX":0.5,"pointY":0.5}},"objectID":"903782E3-C9EE-489A-81E6-A62D2A7D9449","layers":[{"animations":[],"layers":[],"texturedRectangle":{"singleTextureOpacity":1,"textXHeight":0,"shapePath":{"lineWidth":1,"flatness":0.59999999999999998,"lineCapStyle":0,"elements":[{"type":"MoveToPoint","points":[[16.900000000000091,28.800000000000011]]},{"type":"AddLine","points":[[16.900000000000091,32.800000000000011]]},{"type":"AddLine","points":[[16.900000000000091,122.90000000000003]]}],"windingRule":0,"lineJoinStyle":0,"miterLimit":10},"isBackgroundTexture":true,"textBaseline":0,"isVerticalText":false,"textureType":5},"initialState":{"affineTransform":[1,0,0,1,0,0],"masksToBounds":false,"rotation":0,"scale":1,"position":{"pointX":15.699999999999932,"pointY":60.399999999999977},"width":34,"sublayerTransform":[1,0,0,0,0,1,0,0,0,0,1,0,0,0,0,1],"contentsRect":{"y":0,"x":0,"width":1,"height":1},"opacity":1,"edgeAntialiasingMask":0,"height":124,"hidden":true,"anchorPoint":{"pointX":0.5,"pointY":0.5}},"texture":"73E42203A74861E56ECA3E130B16097A"}]}]},{"animations":[],"initialState":{"affineTransform":[1,0,0,1,0,0],"masksToBounds":false,"rotation":0,"scale":1,"position":{"pointX":960,"pointY":540},"width":1920,"sublayerTransform":[1,0,0,0,0,1,0,0,0,0,1,0,0,0,0,1],"contentsRect":{"y":0,"x":0,"width":1,"height":1},"opacity":1,"edgeAntialiasingMask":251658240,"height":1080,"hidden":false,"anchorPoint":{"pointX":0.5,"pointY":0.5}},"layers":[{"animations":[],"initialState":{"affineTransform":[1,0,0,1,0,0],"masksToBounds":false,"rotation":0,"scale":1,"position":{"pointX":757.60000000000002,"pointY":494.70000000000005},"width":441,"sublayerTransform":[1,0,0,0,0,1,0,0,0,0,1,0,0,0,0,1],"contentsRect":{"y":0,"x":0,"width":1,"height":1},"opacity":1,"edgeAntialiasingMask":251658240,"height":143,"hidden":false,"anchorPoint":{"pointX":0.5,"pointY":0.5}},"objectID":"AE2C191D-1DEF-4609-88E0-7F29F0EAF20C","layers":[{"animations":[],"layers":[],"texturedRectangle":{"singleTextureOpacity":1,"textXHeight":0,"shapePath":{"lineWidth":1,"flatness":0.59999999999999998,"lineCapStyle":0,"elements":[{"type":"MoveToPoint","points":[[423.90000000000009,28.400000000000034]]},{"type":"AddLine","points":[[423.90000000000009,32.400000000000034]]},{"type":"AddLine","points":[[423.90000000000009,68.100000000000023]]},{"type":"AddLine","points":[[5.1000000000000227,68.100000000000023]]},{"type":"AddLine","points":[[5.1000000000000227,141.10000000000002]]}],"windingRule":0,"lineJoinStyle":0,"miterLimit":10},"isBackgroundTexture":true,"textBaseline":0,"isVerticalText":false,"textureType":5},"initialState":{"affineTransform":[1,0,0,1,0,0],"masksToBounds":false,"rotation":0,"scale":1,"position":{"pointX":219.39999999999998,"pointY":70.299999999999955},"width":441,"sublayerTransform":[1,0,0,0,0,1,0,0,0,0,1,0,0,0,0,1],"contentsRect":{"y":0,"x":0,"width":1,"height":1},"opacity":1,"edgeAntialiasingMask":0,"height":143,"hidden":true,"anchorPoint":{"pointX":0.5,"pointY":0.5}},"texture":"D4535E46D712DA438D540C50849987E9"}]}]},{"animations":[],"initialState":{"affineTransform":[1,0,0,1,0,0],"masksToBounds":false,"rotation":0,"scale":1,"position":{"pointX":960,"pointY":540},"width":1920,"sublayerTransform":[1,0,0,0,0,1,0,0,0,0,1,0,0,0,0,1],"contentsRect":{"y":0,"x":0,"width":1,"height":1},"opacity":1,"edgeAntialiasingMask":251658240,"height":1080,"hidden":false,"anchorPoint":{"pointX":0.5,"pointY":0.5}},"layers":[{"animations":[],"initialState":{"affineTransform":[1,0,0,1,0,0],"masksToBounds":false,"rotation":0,"scale":1,"position":{"pointX":1164.8000000000002,"pointY":494.70000000000005},"width":441,"sublayerTransform":[1,0,0,0,0,1,0,0,0,0,1,0,0,0,0,1],"contentsRect":{"y":0,"x":0,"width":1,"height":1},"opacity":1,"edgeAntialiasingMask":251658240,"height":143,"hidden":false,"anchorPoint":{"pointX":0.5,"pointY":0.5}},"objectID":"6AA4FBB7-6B28-4C94-8B13-9A1D63CDD70F","layers":[{"animations":[],"layers":[],"texturedRectangle":{"singleTextureOpacity":1,"textXHeight":0,"shapePath":{"lineWidth":1,"flatness":0.59999999999999998,"lineCapStyle":0,"elements":[{"type":"MoveToPoint","points":[[16.900000000000091,28.400000000000034]]},{"type":"AddLine","points":[[16.900000000000091,32.400000000000034]]},{"type":"AddLine","points":[[16.900000000000091,68.100000000000023]]},{"type":"AddLine","points":[[435.80000000000018,68.100000000000023]]},{"type":"AddLine","points":[[435.80000000000018,141.10000000000002]]}],"windingRule":0,"lineJoinStyle":0,"miterLimit":10},"isBackgroundTexture":true,"textBaseline":0,"isVerticalText":false,"textureType":5},"initialState":{"affineTransform":[1,0,0,1,0,0],"masksToBounds":false,"rotation":0,"scale":1,"position":{"pointX":219.19999999999993,"pointY":70.299999999999955},"width":441,"sublayerTransform":[1,0,0,0,0,1,0,0,0,0,1,0,0,0,0,1],"contentsRect":{"y":0,"x":0,"width":1,"height":1},"opacity":1,"edgeAntialiasingMask":0,"height":143,"hidden":true,"anchorPoint":{"pointX":0.5,"pointY":0.5}},"texture":"DBD44AC5EC23EE3DF080EA173AE7C574"}]}]},{"animations":[],"initialState":{"affineTransform":[1,0,0,1,0,0],"masksToBounds":false,"rotation":0,"scale":1,"position":{"pointX":960,"pointY":540},"width":1920,"sublayerTransform":[1,0,0,0,0,1,0,0,0,0,1,0,0,0,0,1],"contentsRect":{"y":0,"x":0,"width":1,"height":1},"opacity":1,"edgeAntialiasingMask":251658240,"height":1080,"hidden":false,"anchorPoint":{"pointX":0.5,"pointY":0.5}},"layers":[{"animations":[],"initialState":{"affineTransform":[1,0,0,1,0,0],"masksToBounds":false,"rotation":0,"scale":1,"position":{"pointX":1380.2000000000003,"pointY":759.90000000000009},"width":34,"sublayerTransform":[1,0,0,0,0,1,0,0,0,0,1,0,0,0,0,1],"contentsRect":{"y":0,"x":0,"width":1,"height":1},"opacity":1,"edgeAntialiasingMask":251658240,"height":143,"hidden":false,"anchorPoint":{"pointX":0.5,"pointY":0.5}},"objectID":"BDEFA4D4-23C8-47F1-8AD2-9A3A16CC66F4","layers":[{"animations":[],"layers":[],"texturedRectangle":{"singleTextureOpacity":1,"textXHeight":0,"shapePath":{"lineWidth":1,"flatness":0.59999999999999998,"lineCapStyle":0,"elements":[{"type":"MoveToPoint","points":[[16.800000000000182,28.600000000000136]]},{"type":"AddLine","points":[[16.800000000000182,32.600000000000136]]},{"type":"AddLine","points":[[16.800000000000182,141.40000000000009]]}],"windingRule":0,"lineJoinStyle":0,"miterLimit":10},"isBackgroundTexture":true,"textBaseline":0,"isVerticalText":false,"textureType":5},"initialState":{"affineTransform":[1,0,0,1,0,0],"masksToBounds":false,"rotation":0,"scale":1,"position":{"pointX":15.799999999999727,"pointY":70.099999999999909},"width":34,"sublayerTransform":[1,0,0,0,0,1,0,0,0,0,1,0,0,0,0,1],"contentsRect":{"y":0,"x":0,"width":1,"height":1},"opacity":1,"edgeAntialiasingMask":0,"height":143,"hidden":true,"anchorPoint":{"pointX":0.5,"pointY":0.5}},"texture":"370936F4C116E35A4E4E20C10E9D5053"}]}]}]}},{"effects":[{"beginTime":0,"baseLayer":{"animations":[],"initialState":{"affineTransform":[1,0,0,1,0,0],"masksToBounds":false,"rotation":0,"scale":1,"position":{"pointX":961.30000000000007,"pointY":238.60000000000002},"width":34,"sublayerTransform":[1,0,0,0,0,1,0,0,0,0,1,0,0,0,0,1],"contentsRect":{"y":0,"x":0,"width":1,"height":1},"opacity":1,"edgeAntialiasingMask":251658240,"height":124,"hidden":false,"anchorPoint":{"pointX":0.5,"pointY":0.5}},"objectID":"B40CEB66-27F9-4E74-BF73-EE1640227C05","layers":[{"animations":[],"initialState":{"affineTransform":[1,0,0,1,0,0],"masksToBounds":false,"rotation":0,"scale":1,"position":{"pointX":15.699999999999932,"pointY":363.39999999999998},"width":34,"sublayerTransform":[1,0,0,0,0,1,0,0,0,0,1,-0.00035007912466775983,0,0,0,1],"contentsRect":{"y":0,"x":0,"width":1,"height":1},"opacity":1,"edgeAntialiasingMask":251658240,"height":124,"hidden":false,"anchorPoint":{"pointX":0.46176470588235091,"pointY":2.9306451612903226}},"layers":[{"animations":[{"timeOffset":0,"beginTime":1e-100,"repeatCount":0,"animations":[{"timeOffset":0,"from":{"scalar":1},"beginTime":0,"repeatCount":0,"fillMode":"both","duration":0.29999999999999999,"autoreverses":false,"timingFunction":"EaseInEaseOut","property":"opacity","to":{"scalar":0}}],"fillMode":"both","autoreverses":false,"duration":0.29999999999999999}],"layers":[],"texturedRectangle":{"singleTextureOpacity":1,"textXHeight":0,"shapePath":{"lineWidth":1,"flatness":0.59999999999999998,"lineCapStyle":0,"elements":[{"type":"MoveToPoint","points":[[16.900000000000091,1.6000000000000227]]},{"type":"AddLine","points":[[16.900000000000091,91.700000000000045]]},{"type":"AddLine","points":[[16.900000000000091,95.700000000000045]]}],"windingRule":0,"lineJoinStyle":0,"miterLimit":10},"isBackgroundTexture":true,"textBaseline":0,"isVerticalText":false,"textureType":5},"initialState":{"affineTransform":[1,0,0,1,0,0],"masksToBounds":false,"rotation":0,"scale":1,"position":{"pointX":15.699999999999932,"pointY":60.399999999999977},"width":34,"sublayerTransform":[1,0,0,0,0,1,0,0,0,0,1,0,0,0,0,1],"contentsRect":{"y":0,"x":0,"width":1,"height":1},"opacity":1,"edgeAntialiasingMask":0,"height":124,"hidden":false,"anchorPoint":{"pointX":0.5,"pointY":0.5}},"texture":"0FEF2B786609238E24DCBD6FA003DA71"}]}]},"effects":[],"duration":0.29999999999999999,"type":"buildOut","name":"apple:dissolve character","objectID":"B40CEB66-27F9-4E74-BF73-EE1640227C05"},{"beginTime":0,"baseLayer":{"animations":[],"initialState":{"affineTransform":[1,0,0,1,0,0],"masksToBounds":false,"rotation":0,"scale":1,"position":{"pointX":746,"pointY":494.70000000000005},"width":441,"sublayerTransform":[1,0,0,0,0,1,0,0,0,0,1,0,0,0,0,1],"contentsRect":{"y":0,"x":0,"width":1,"height":1},"opacity":1,"edgeAntialiasingMask":251658240,"height":143,"hidden":false,"anchorPoint":{"pointX":0.5,"pointY":0.5}},"objectID":"D50B8826-71B6-4A0D-9E46-08E58B3CC3F7","layers":[{"animations":[],"initialState":{"affineTransform":[1,0,0,1,0,0],"masksToBounds":false,"rotation":0,"scale":1,"position":{"pointX":434.5,"pointY":116.79999999999995},"width":441,"sublayerTransform":[1,0,0,0,0,1,0,0,0,0,1,-0.00035007912466775983,0,0,0,1],"contentsRect":{"y":0,"x":0,"width":1,"height":1},"opacity":1,"edgeAntialiasingMask":251658240,"height":143,"hidden":false,"anchorPoint":{"pointX":0.98526077097505671,"pointY":0.81678321678321641}},"layers":[{"animations":[{"timeOffset":0,"beginTime":1e-100,"repeatCount":0,"animations":[{"timeOffset":0,"from":{"scalar":1},"beginTime":0,"repeatCount":0,"fillMode":"both","duration":0.29999999999999999,"autoreverses":false,"timingFunction":"EaseInEaseOut","property":"opacity","to":{"scalar":0}}],"fillMode":"both","autoreverses":false,"duration":0.29999999999999999}],"layers":[],"texturedRectangle":{"singleTextureOpacity":1,"textXHeight":0,"shapePath":{"lineWidth":1,"flatness":0.59999999999999998,"lineCapStyle":0,"elements":[{"type":"MoveToPoint","points":[[435.90000000000009,1.2000000000000455]]},{"type":"AddLine","points":[[435.90000000000009,68.100000000000023]]},{"type":"AddLine","points":[[17.100000000000023,68.100000000000023]]},{"type":"AddLine","points":[[17.100000000000023,109.89999999999998]]},{"type":"AddLine","points":[[17.100000000000023,113.89999999999998]]}],"windingRule":0,"lineJoinStyle":0,"miterLimit":10},"isBackgroundTexture":true,"textBaseline":0,"isVerticalText":false,"textureType":5},"initialState":{"affineTransform":[1,0,0,1,0,0],"masksToBounds":false,"rotation":0,"scale":1,"position":{"pointX":219,"pointY":70.299999999999955},"width":441,"sublayerTransform":[1,0,0,0,0,1,0,0,0,0,1,0,0,0,0,1],"contentsRect":{"y":0,"x":0,"width":1,"height":1},"opacity":1,"edgeAntialiasingMask":0,"height":143,"hidden":false,"anchorPoint":{"pointX":0.5,"pointY":0.5}},"texture":"9211CEF4A32EFCE19DDE0CF9CF6F5DB5"}]}]},"effects":[],"duration":0.29999999999999999,"type":"buildOut","name":"apple:dissolve character","objectID":"D50B8826-71B6-4A0D-9E46-08E58B3CC3F7"},{"beginTime":0,"baseLayer":{"animations":[],"initialState":{"affineTransform":[1,0,0,1,0,0],"masksToBounds":false,"rotation":0,"scale":1,"position":{"pointX":1176.9000000000001,"pointY":494.70000000000005},"width":442,"sublayerTransform":[1,0,0,0,0,1,0,0,0,0,1,0,0,0,0,1],"contentsRect":{"y":0,"x":0,"width":1,"height":1},"opacity":1,"edgeAntialiasingMask":251658240,"height":143,"hidden":false,"anchorPoint":{"pointX":0.5,"pointY":0.5}},"objectID":"DD1B31DF-6619-4B5D-8A79-8C6F30D76B17","layers":[{"animations":[],"initialState":{"affineTransform":[1,0,0,1,0,0],"masksToBounds":false,"rotation":0,"scale":1,"position":{"pointX":4.0999999999999091,"pointY":116.79999999999995},"width":442,"sublayerTransform":[1,0,0,0,0,1,0,0,0,0,1,-0.00035007912466775983,0,0,0,1],"contentsRect":{"y":0,"x":0,"width":1,"height":1},"opacity":1,"edgeAntialiasingMask":251658240,"height":143,"hidden":false,"anchorPoint":{"pointX":0.0092760180995473049,"pointY":0.81678321678321641}},"layers":[{"animations":[{"timeOffset":0,"beginTime":1e-100,"repeatCount":0,"animations":[{"timeOffset":0,"from":{"scalar":1},"beginTime":0,"repeatCount":0,"fillMode":"both","duration":0.29999999999999999,"autoreverses":false,"timingFunction":"EaseInEaseOut","property":"opacity","to":{"scalar":0}}],"fillMode":"both","autoreverses":false,"duration":0.29999999999999999}],"layers":[],"texturedRectangle":{"singleTextureOpacity":1,"textXHeight":0,"shapePath":{"lineWidth":1,"flatness":0.59999999999999998,"lineCapStyle":0,"elements":[{"type":"MoveToPoint","points":[[5.9000000000000909,1.2000000000000455]]},{"type":"AddLine","points":[[5.9000000000000909,68.100000000000023]]},{"type":"AddLine","points":[[424.80000000000018,68.100000000000023]]},{"type":"AddLine","points":[[424.80000000000018,109.89999999999998]]},{"type":"AddLine","points":[[424.80000000000018,113.89999999999998]]}],"windingRule":0,"lineJoinStyle":0,"miterLimit":10},"isBackgroundTexture":true,"textBaseline":0,"isVerticalText":false,"textureType":5},"initialState":{"affineTransform":[1,0,0,1,0,0],"masksToBounds":false,"rotation":0,"scale":1,"position":{"pointX":219.09999999999991,"pointY":70.299999999999955},"width":442,"sublayerTransform":[1,0,0,0,0,1,0,0,0,0,1,0,0,0,0,1],"contentsRect":{"y":0,"x":0,"width":1,"height":1},"opacity":1,"edgeAntialiasingMask":0,"height":143,"hidden":false,"anchorPoint":{"pointX":0.5,"pointY":0.5}},"texture":"08F420D27E33D0EC9CABBBFB1CBFCF70"}]}]},"effects":[],"duration":0.29999999999999999,"type":"buildOut","name":"apple:dissolve character","objectID":"DD1B31DF-6619-4B5D-8A79-8C6F30D76B17"},{"beginTime":0,"baseLayer":{"animations":[],"initialState":{"affineTransform":[1,0,0,1,0,0],"masksToBounds":false,"rotation":0,"scale":1,"position":{"pointX":1380.2000000000003,"pointY":759.90000000000009},"width":34,"sublayerTransform":[1,0,0,0,0,1,0,0,0,0,1,0,0,0,0,1],"contentsRect":{"y":0,"x":0,"width":1,"height":1},"opacity":1,"edgeAntialiasingMask":251658240,"height":143,"hidden":false,"anchorPoint":{"pointX":0.5,"pointY":0.5}},"objectID":"71C7034D-C2C2-41A7-8910-3A95DFFF9E37","layers":[{"animations":[],"initialState":{"affineTransform":[1,0,0,1,0,0],"masksToBounds":false,"rotation":0,"scale":1,"position":{"pointX":-403.20000000000027,"pointY":-148.40000000000009},"width":34,"sublayerTransform":[1,0,0,0,0,1,0,0,0,0,1,-0.00035007912466775983,0,0,0,1],"contentsRect":{"y":0,"x":0,"width":1,"height":1},"opacity":1,"edgeAntialiasingMask":251658240,"height":143,"hidden":false,"anchorPoint":{"pointX":-11.858823529411772,"pointY":-1.0377622377622384}},"layers":[{"animations":[{"timeOffset":0,"beginTime":1e-100,"repeatCount":0,"animations":[{"timeOffset":0,"from":{"scalar":1},"beginTime":0,"repeatCount":0,"fillMode":"both","duration":0.29999999999999999,"autoreverses":false,"timingFunction":"EaseInEaseOut","property":"opacity","to":{"scalar":0}}],"fillMode":"both","autoreverses":false,"duration":0.29999999999999999}],"layers":[],"texturedRectangle":{"singleTextureOpacity":1,"textXHeight":0,"shapePath":{"lineWidth":1,"flatness":0.59999999999999998,"lineCapStyle":0,"elements":[{"type":"MoveToPoint","points":[[16.800000000000182,1.4000000000000909]]},{"type":"AddLine","points":[[16.800000000000182,110.20000000000005]]},{"type":"AddLine","points":[[16.800000000000182,114.20000000000005]]}],"windingRule":0,"lineJoinStyle":0,"miterLimit":10},"isBackgroundTexture":true,"textBaseline":0,"isVerticalText":false,"textureType":5},"initialState":{"affineTransform":[1,0,0,1,0,0],"masksToBounds":false,"rotation":0,"scale":1,"position":{"pointX":15.799999999999727,"pointY":70.099999999999909},"width":34,"sublayerTransform":[1,0,0,0,0,1,0,0,0,0,1,0,0,0,0,1],"contentsRect":{"y":0,"x":0,"width":1,"height":1},"opacity":1,"edgeAntialiasingMask":0,"height":143,"hidden":false,"anchorPoint":{"pointX":0.5,"pointY":0.5}},"texture":"C2A54592E8BA3E35D010F868277412E0"}]}]},"effects":[{"beginTime":0,"baseLayer":{"animations":[],"initialState":{"affineTransform":[1,0,0,1,0,0],"masksToBounds":false,"rotation":0,"scale":1,"position":{"pointX":961.30000000000007,"pointY":238.60000000000002},"width":34,"sublayerTransform":[1,0,0,0,0,1,0,0,0,0,1,0,0,0,0,1],"contentsRect":{"y":0,"x":0,"width":1,"height":1},"opacity":1,"edgeAntialiasingMask":251658240,"height":124,"hidden":false,"anchorPoint":{"pointX":0.5,"pointY":0.5}},"objectID":"903782E3-C9EE-489A-81E6-A62D2A7D9449","layers":[{"animations":[],"initialState":{"affineTransform":[1,0,0,1,0,0],"masksToBounds":false,"rotation":0,"scale":1,"position":{"pointX":15.699999999999932,"pointY":363.39999999999998},"width":34,"sublayerTransform":[1,0,0,0,0,1,0,0,0,0,1,-0.00035007912466775983,0,0,0,1],"contentsRect":{"y":0,"x":0,"width":1,"height":1},"opacity":1,"edgeAntialiasingMask":251658240,"height":124,"hidden":false,"anchorPoint":{"pointX":0.46176470588235091,"pointY":2.9306451612903226}},"layers":[{"animations":[{"timeOffset":0,"beginTime":1e-100,"repeatCount":0,"animations":[{"timeOffset":0,"from":{"scalar":0},"beginTime":0,"repeatCount":0,"fillMode":"both","duration":0.29999999999999999,"autoreverses":false,"timingFunction":"EaseInEaseOut","property":"opacity","to":{"scalar":1}},{"timeOffset":0,"from":{"scalar":false},"beginTime":0,"repeatCount":0,"fillMode":"forwards","property":"hidden","autoreverses":false,"duration":0.29999999999999999,"to":{"scalar":false}}],"fillMode":"both","autoreverses":false,"duration":0.29999999999999999}],"layers":[],"texturedRectangle":{"singleTextureOpacity":1,"textXHeight":0,"shapePath":{"lineWidth":1,"flatness":0.59999999999999998,"lineCapStyle":0,"elements":[{"type":"MoveToPoint","points":[[16.900000000000091,28.800000000000011]]},{"type":"AddLine","points":[[16.900000000000091,32.800000000000011]]},{"type":"AddLine","points":[[16.900000000000091,122.90000000000003]]}],"windingRule":0,"lineJoinStyle":0,"miterLimit":10},"isBackgroundTexture":true,"textBaseline":0,"isVerticalText":false,"textureType":5},"initialState":{"affineTransform":[1,0,0,1,0,0],"masksToBounds":false,"rotation":0,"scale":1,"position":{"pointX":15.699999999999932,"pointY":60.399999999999977},"width":34,"sublayerTransform":[1,0,0,0,0,1,0,0,0,0,1,0,0,0,0,1],"contentsRect":{"y":0,"x":0,"width":1,"height":1},"opacity":1,"edgeAntialiasingMask":0,"height":124,"hidden":true,"anchorPoint":{"pointX":0.5,"pointY":0.5}},"texture":"73E42203A74861E56ECA3E130B16097A"}]}]},"effects":[],"duration":0.29999999999999999,"type":"buildIn","name":"apple:dissolve character","objectID":"903782E3-C9EE-489A-81E6-A62D2A7D9449"},{"beginTime":0,"baseLayer":{"animations":[],"initialState":{"affineTransform":[1,0,0,1,0,0],"masksToBounds":false,"rotation":0,"scale":1,"position":{"pointX":757.60000000000002,"pointY":494.70000000000005},"width":441,"sublayerTransform":[1,0,0,0,0,1,0,0,0,0,1,0,0,0,0,1],"contentsRect":{"y":0,"x":0,"width":1,"height":1},"opacity":1,"edgeAntialiasingMask":251658240,"height":143,"hidden":false,"anchorPoint":{"pointX":0.5,"pointY":0.5}},"objectID":"AE2C191D-1DEF-4609-88E0-7F29F0EAF20C","layers":[{"animations":[],"initialState":{"affineTransform":[1,0,0,1,0,0],"masksToBounds":false,"rotation":0,"scale":1,"position":{"pointX":422.89999999999998,"pointY":116.79999999999995},"width":441,"sublayerTransform":[1,0,0,0,0,1,0,0,0,0,1,-0.00035007912466775983,0,0,0,1],"contentsRect":{"y":0,"x":0,"width":1,"height":1},"opacity":1,"edgeAntialiasingMask":251658240,"height":143,"hidden":false,"anchorPoint":{"pointX":0.95895691609977318,"pointY":0.81678321678321641}},"layers":[{"animations":[{"timeOffset":0,"beginTime":1e-100,"repeatCount":0,"animations":[{"timeOffset":0,"from":{"scalar":0},"beginTime":0,"repeatCount":0,"fillMode":"both","duration":0.29999999999999999,"autoreverses":false,"timingFunction":"EaseInEaseOut","property":"opacity","to":{"scalar":1}},{"timeOffset":0,"from":{"scalar":false},"beginTime":0,"repeatCount":0,"fillMode":"forwards","property":"hidden","autoreverses":false,"duration":0.29999999999999999,"to":{"scalar":false}}],"fillMode":"both","autoreverses":false,"duration":0.29999999999999999}],"layers":[],"texturedRectangle":{"singleTextureOpacity":1,"textXHeight":0,"shapePath":{"lineWidth":1,"flatness":0.59999999999999998,"lineCapStyle":0,"elements":[{"type":"MoveToPoint","points":[[423.90000000000009,28.400000000000034]]},{"type":"AddLine","points":[[423.90000000000009,32.400000000000034]]},{"type":"AddLine","points":[[423.90000000000009,68.100000000000023]]},{"type":"AddLine","points":[[5.1000000000000227,68.100000000000023]]},{"type":"AddLine","points":[[5.1000000000000227,141.10000000000002]]}],"windingRule":0,"lineJoinStyle":0,"miterLimit":10},"isBackgroundTexture":true,"textBaseline":0,"isVerticalText":false,"textureType":5},"initialState":{"affineTransform":[1,0,0,1,0,0],"masksToBounds":false,"rotation":0,"scale":1,"position":{"pointX":219.39999999999998,"pointY":70.299999999999955},"width":441,"sublayerTransform":[1,0,0,0,0,1,0,0,0,0,1,0,0,0,0,1],"contentsRect":{"y":0,"x":0,"width":1,"height":1},"opacity":1,"edgeAntialiasingMask":0,"height":143,"hidden":true,"anchorPoint":{"pointX":0.5,"pointY":0.5}},"texture":"D4535E46D712DA438D540C50849987E9"}]}]},"effects":[],"duration":0.29999999999999999,"type":"buildIn","name":"apple:dissolve character","objectID":"AE2C191D-1DEF-4609-88E0-7F29F0EAF20C"},{"beginTime":0,"baseLayer":{"animations":[],"initialState":{"affineTransform":[1,0,0,1,0,0],"masksToBounds":false,"rotation":0,"scale":1,"position":{"pointX":1164.8000000000002,"pointY":494.70000000000005},"width":441,"sublayerTransform":[1,0,0,0,0,1,0,0,0,0,1,0,0,0,0,1],"contentsRect":{"y":0,"x":0,"width":1,"height":1},"opacity":1,"edgeAntialiasingMask":251658240,"height":143,"hidden":false,"anchorPoint":{"pointX":0.5,"pointY":0.5}},"objectID":"6AA4FBB7-6B28-4C94-8B13-9A1D63CDD70F","layers":[{"animations":[],"initialState":{"affineTransform":[1,0,0,1,0,0],"masksToBounds":false,"rotation":0,"scale":1,"position":{"pointX":15.699999999999818,"pointY":116.79999999999995},"width":441,"sublayerTransform":[1,0,0,0,0,1,0,0,0,0,1,-0.00035007912466775983,0,0,0,1],"contentsRect":{"y":0,"x":0,"width":1,"height":1},"opacity":1,"edgeAntialiasingMask":251658240,"height":143,"hidden":false,"anchorPoint":{"pointX":0.035600907029478046,"pointY":0.81678321678321641}},"layers":[{"animations":[{"timeOffset":0,"beginTime":1e-100,"repeatCount":0,"animations":[{"timeOffset":0,"from":{"scalar":0},"beginTime":0,"repeatCount":0,"fillMode":"both","duration":0.29999999999999999,"autoreverses":false,"timingFunction":"EaseInEaseOut","property":"opacity","to":{"scalar":1}},{"timeOffset":0,"from":{"scalar":false},"beginTime":0,"repeatCount":0,"fillMode":"forwards","property":"hidden","autoreverses":false,"duration":0.29999999999999999,"to":{"scalar":false}}],"fillMode":"both","autoreverses":false,"duration":0.29999999999999999}],"layers":[],"texturedRectangle":{"singleTextureOpacity":1,"textXHeight":0,"shapePath":{"lineWidth":1,"flatness":0.59999999999999998,"lineCapStyle":0,"elements":[{"type":"MoveToPoint","points":[[16.900000000000091,28.400000000000034]]},{"type":"AddLine","points":[[16.900000000000091,32.400000000000034]]},{"type":"AddLine","points":[[16.900000000000091,68.100000000000023]]},{"type":"AddLine","points":[[435.80000000000018,68.100000000000023]]},{"type":"AddLine","points":[[435.80000000000018,141.10000000000002]]}],"windingRule":0,"lineJoinStyle":0,"miterLimit":10},"isBackgroundTexture":true,"textBaseline":0,"isVerticalText":false,"textureType":5},"initialState":{"affineTransform":[1,0,0,1,0,0],"masksToBounds":false,"rotation":0,"scale":1,"position":{"pointX":219.19999999999993,"pointY":70.299999999999955},"width":441,"sublayerTransform":[1,0,0,0,0,1,0,0,0,0,1,0,0,0,0,1],"contentsRect":{"y":0,"x":0,"width":1,"height":1},"opacity":1,"edgeAntialiasingMask":0,"height":143,"hidden":true,"anchorPoint":{"pointX":0.5,"pointY":0.5}},"texture":"DBD44AC5EC23EE3DF080EA173AE7C574"}]}]},"effects":[],"duration":0.29999999999999999,"type":"buildIn","name":"apple:dissolve character","objectID":"6AA4FBB7-6B28-4C94-8B13-9A1D63CDD70F"},{"beginTime":0,"baseLayer":{"animations":[],"initialState":{"affineTransform":[1,0,0,1,0,0],"masksToBounds":false,"rotation":0,"scale":1,"position":{"pointX":1380.2000000000003,"pointY":759.90000000000009},"width":34,"sublayerTransform":[1,0,0,0,0,1,0,0,0,0,1,0,0,0,0,1],"contentsRect":{"y":0,"x":0,"width":1,"height":1},"opacity":1,"edgeAntialiasingMask":251658240,"height":143,"hidden":false,"anchorPoint":{"pointX":0.5,"pointY":0.5}},"objectID":"BDEFA4D4-23C8-47F1-8AD2-9A3A16CC66F4","layers":[{"animations":[],"initialState":{"affineTransform":[1,0,0,1,0,0],"masksToBounds":false,"rotation":0,"scale":1,"position":{"pointX":-403.20000000000027,"pointY":-148.40000000000009},"width":34,"sublayerTransform":[1,0,0,0,0,1,0,0,0,0,1,-0.00035007912466775983,0,0,0,1],"contentsRect":{"y":0,"x":0,"width":1,"height":1},"opacity":1,"edgeAntialiasingMask":251658240,"height":143,"hidden":false,"anchorPoint":{"pointX":-11.858823529411772,"pointY":-1.0377622377622384}},"layers":[{"animations":[{"timeOffset":0,"beginTime":1e-100,"repeatCount":0,"animations":[{"timeOffset":0,"from":{"scalar":0},"beginTime":0,"repeatCount":0,"fillMode":"both","duration":0.29999999999999999,"autoreverses":false,"timingFunction":"EaseInEaseOut","property":"opacity","to":{"scalar":1}},{"timeOffset":0,"from":{"scalar":false},"beginTime":0,"repeatCount":0,"fillMode":"forwards","property":"hidden","autoreverses":false,"duration":0.29999999999999999,"to":{"scalar":false}}],"fillMode":"both","autoreverses":false,"duration":0.29999999999999999}],"layers":[],"texturedRectangle":{"singleTextureOpacity":1,"textXHeight":0,"shapePath":{"lineWidth":1,"flatness":0.59999999999999998,"lineCapStyle":0,"elements":[{"type":"MoveToPoint","points":[[16.800000000000182,28.600000000000136]]},{"type":"AddLine","points":[[16.800000000000182,32.600000000000136]]},{"type":"AddLine","points":[[16.800000000000182,141.40000000000009]]}],"windingRule":0,"lineJoinStyle":0,"miterLimit":10},"isBackgroundTexture":true,"textBaseline":0,"isVerticalText":false,"textureType":5},"initialState":{"affineTransform":[1,0,0,1,0,0],"masksToBounds":false,"rotation":0,"scale":1,"position":{"pointX":15.799999999999727,"pointY":70.099999999999909},"width":34,"sublayerTransform":[1,0,0,0,0,1,0,0,0,0,1,0,0,0,0,1],"contentsRect":{"y":0,"x":0,"width":1,"height":1},"opacity":1,"edgeAntialiasingMask":0,"height":143,"hidden":true,"anchorPoint":{"pointX":0.5,"pointY":0.5}},"texture":"370936F4C116E35A4E4E20C10E9D5053"}]}]},"effects":[],"duration":0.29999999999999999,"type":"buildIn","name":"apple:dissolve character","objectID":"BDEFA4D4-23C8-47F1-8AD2-9A3A16CC66F4"}],"duration":0.29999999999999999,"type":"buildOut","name":"apple:dissolve character","objectID":"71C7034D-C2C2-41A7-8910-3A95DFFF9E37"}],"automaticPlay":false,"hyperlinks":[],"accessibility":[{"text":"<search-movies-box\/>","targetRectangle":{"y":601.19805908203125,"x":319.39675903320312,"width":443.54296875,"height":50}},{"text":"<movies-list\/>","targetRectangle":{"y":601.19805908203125,"x":1238.7633972167969,"width":280.13671875,"height":50}},{"text":"<movies-list-item\/>","targetRectangle":{"y":866.4183349609375,"x":1188.5910339355469,"width":380.4814453125,"height":50}},{"text":"<search-movies-page\/>","targetRectangle":{"y":335.97772216796875,"x":726.54928588867188,"width":466.9013671875,"height":50}},{"text":"outside world","targetRectangle":{"y":57.746328443288803,"x":761.20310890674591,"width":397.59375,"height":61.5703125}}],"baseLayer":{"animations":[],"initialState":{"affineTransform":[1,0,0,1,0,0],"masksToBounds":false,"rotation":0,"scale":1,"position":{"pointX":960,"pointY":540},"width":1920,"sublayerTransform":[1,0,0,0,0,1,0,0,0,0,1,0,0,0,0,1],"contentsRect":{"y":0,"x":0,"width":1,"height":1},"opacity":1,"edgeAntialiasingMask":251658240,"height":1080,"hidden":false,"anchorPoint":{"pointX":0.5,"pointY":0.5}},"layers":[{"animations":[],"initialState":{"affineTransform":[1,0,0,1,0,0],"masksToBounds":false,"rotation":0,"scale":1,"position":{"pointX":960,"pointY":540},"width":1920,"sublayerTransform":[1,0,0,0,0,1,0,0,0,0,1,0,0,0,0,1],"contentsRect":{"y":0,"x":0,"width":1,"height":1},"opacity":1,"edgeAntialiasingMask":251658240,"height":1080,"hidden":false,"anchorPoint":{"pointX":0.5,"pointY":0.5}},"layers":[{"animations":[],"initialState":{"affineTransform":[1,0,0,1,0,0],"masksToBounds":false,"rotation":0,"scale":1,"position":{"pointX":960,"pointY":540},"width":1920,"sublayerTransform":[1,0,0,0,0,1,0,0,0,0,1,0,0,0,0,1],"contentsRect":{"y":0,"x":0,"width":1,"height":1},"opacity":1,"edgeAntialiasingMask":251658240,"height":1080,"hidden":false,"anchorPoint":{"pointX":0.5,"pointY":0.5}},"layers":[{"animations":[],"layers":[],"texturedRectangle":{"isBackgroundTexture":true,"singleTextureOpacity":1,"textureType":1,"textBaseline":0,"textXHeight":0,"isVerticalText":false},"initialState":{"affineTransform":[1,0,0,1,0,0],"masksToBounds":false,"rotation":0,"scale":1,"position":{"pointX":960,"pointY":540},"width":1920,"sublayerTransform":[1,0,0,0,0,1,0,0,0,0,1,0,0,0,0,1],"contentsRect":{"y":0,"x":0,"width":1,"height":1},"opacity":1,"edgeAntialiasingMask":0,"height":1080,"hidden":false,"anchorPoint":{"pointX":0.5,"pointY":0.5}},"texture":"63320DF3585E5970F64F12FDA3FAB4CB"}]}]},{"animations":[],"initialState":{"affineTransform":[1,0,0,1,0,0],"masksToBounds":false,"rotation":0,"scale":1,"position":{"pointX":960,"pointY":540},"width":1920,"sublayerTransform":[1,0,0,0,0,1,0,0,0,0,1,0,0,0,0,1],"contentsRect":{"y":0,"x":0,"width":1,"height":1},"opacity":1,"edgeAntialiasingMask":251658240,"height":1080,"hidden":false,"anchorPoint":{"pointX":0.5,"pointY":0.5}},"layers":[{"animations":[],"initialState":{"affineTransform":[1,0,0,1,0,0],"masksToBounds":false,"rotation":0,"scale":1,"position":{"pointX":961.33447265625,"pointY":362.47772216796875},"width":620,"sublayerTransform":[1,0,0,0,0,1,0,0,0,0,1,0,0,0,0,1],"contentsRect":{"y":0,"x":0,"width":1,"height":1},"opacity":1,"edgeAntialiasingMask":251658240,"height":129,"hidden":false,"anchorPoint":{"pointX":0.5,"pointY":0.5}},"layers":[{"animations":[],"layers":[],"texturedRectangle":{"singleTextureOpacity":1,"textXHeight":0,"shapePath":{"lineWidth":1,"flatness":0.59999999999999998,"lineCapStyle":0,"elements":[{"type":"MoveToPoint","points":[[5.33447265625,5.97772216796875]]},{"type":"AddLine","points":[[614.66546630859375,5.97772216796875]]},{"type":"AddLine","points":[[614.66546630859375,123.26389312744141]]},{"type":"AddLine","points":[[5.33447265625,123.26389312744141]]},{"type":"CloseSubpath"},{"type":"MoveToPoint","points":[[5.33447265625,5.97772216796875]]}],"windingRule":0,"lineJoinStyle":0,"miterLimit":10},"isBackgroundTexture":true,"textBaseline":0,"isVerticalText":false,"textureType":5},"initialState":{"affineTransform":[1,0,0,1,0,0],"masksToBounds":false,"rotation":0,"scale":1,"position":{"pointX":308.66552734375,"pointY":62.52227783203125},"width":620,"sublayerTransform":[1,0,0,0,0,1,0,0,0,0,1,0,0,0,0,1],"contentsRect":{"y":0,"x":0,"width":1,"height":1},"opacity":1,"edgeAntialiasingMask":0,"height":129,"hidden":false,"anchorPoint":{"pointX":0.5,"pointY":0.5}},"texture":"00EF00B3FF14D579613EFF71EF05F5D2"}]}]},{"animations":[],"initialState":{"affineTransform":[1,0,0,1,0,0],"masksToBounds":false,"rotation":0,"scale":1,"position":{"pointX":960,"pointY":540},"width":1920,"sublayerTransform":[1,0,0,0,0,1,0,0,0,0,1,0,0,0,0,1],"contentsRect":{"y":0,"x":0,"width":1,"height":1},"opacity":1,"edgeAntialiasingMask":251658240,"height":1080,"hidden":false,"anchorPoint":{"pointX":0.5,"pointY":0.5}},"layers":[{"animations":[],"initialState":{"affineTransform":[1,0,0,1,0,0],"masksToBounds":false,"rotation":0,"scale":1,"position":{"pointX":542.50274658203125,"pointY":627.19805908203125},"width":620,"sublayerTransform":[1,0,0,0,0,1,0,0,0,0,1,0,0,0,0,1],"contentsRect":{"y":0,"x":0,"width":1,"height":1},"opacity":1,"edgeAntialiasingMask":251658240,"height":128,"hidden":false,"anchorPoint":{"pointX":0.5,"pointY":0.5}},"layers":[{"animations":[],"layers":[],"texturedRectangle":{"singleTextureOpacity":1,"textXHeight":0,"shapePath":{"lineWidth":1,"flatness":0.59999999999999998,"lineCapStyle":0,"elements":[{"type":"MoveToPoint","points":[[5.50274658203125,5.19805908203125]]},{"type":"AddLine","points":[[614.833740234375,5.19805908203125]]},{"type":"AddLine","points":[[614.833740234375,122.48423004150391]]},{"type":"AddLine","points":[[5.50274658203125,122.48423004150391]]},{"type":"CloseSubpath"},{"type":"MoveToPoint","points":[[5.50274658203125,5.19805908203125]]}],"windingRule":0,"lineJoinStyle":0,"miterLimit":10},"isBackgroundTexture":true,"textBaseline":0,"isVerticalText":false,"textureType":5},"initialState":{"affineTransform":[1,0,0,1,0,0],"masksToBounds":false,"rotation":0,"scale":1,"position":{"pointX":308.49725341796875,"pointY":62.80194091796875},"width":620,"sublayerTransform":[1,0,0,0,0,1,0,0,0,0,1,0,0,0,0,1],"contentsRect":{"y":0,"x":0,"width":1,"height":1},"opacity":1,"edgeAntialiasingMask":0,"height":128,"hidden":false,"anchorPoint":{"pointX":0.5,"pointY":0.5}},"texture":"453BE8B0F2DA81A5A63782E720315E21"}]}]},{"animations":[],"initialState":{"affineTransform":[1,0,0,1,0,0],"masksToBounds":false,"rotation":0,"scale":1,"position":{"pointX":960,"pointY":540},"width":1920,"sublayerTransform":[1,0,0,0,0,1,0,0,0,0,1,0,0,0,0,1],"contentsRect":{"y":0,"x":0,"width":1,"height":1},"opacity":1,"edgeAntialiasingMask":251658240,"height":1080,"hidden":false,"anchorPoint":{"pointX":0.5,"pointY":0.5}},"layers":[{"animations":[],"initialState":{"affineTransform":[1,0,0,1,0,0],"masksToBounds":false,"rotation":0,"scale":1,"position":{"pointX":1380.166259765625,"pointY":627.19805908203125},"width":620,"sublayerTransform":[1,0,0,0,0,1,0,0,0,0,1,0,0,0,0,1],"contentsRect":{"y":0,"x":0,"width":1,"height":1},"opacity":1,"edgeAntialiasingMask":251658240,"height":128,"hidden":false,"anchorPoint":{"pointX":0.5,"pointY":0.5}},"layers":[{"animations":[],"layers":[],"texturedRectangle":{"singleTextureOpacity":1,"textXHeight":0,"shapePath":{"lineWidth":1,"flatness":0.59999999999999998,"lineCapStyle":0,"elements":[{"type":"MoveToPoint","points":[[5.166259765625,5.19805908203125]]},{"type":"AddLine","points":[[614.49725341796875,5.19805908203125]]},{"type":"AddLine","points":[[614.49725341796875,122.48423004150391]]},{"type":"AddLine","points":[[5.166259765625,122.48423004150391]]},{"type":"CloseSubpath"},{"type":"MoveToPoint","points":[[5.166259765625,5.19805908203125]]}],"windingRule":0,"lineJoinStyle":0,"miterLimit":10},"isBackgroundTexture":true,"textBaseline":0,"isVerticalText":false,"textureType":5},"initialState":{"affineTransform":[1,0,0,1,0,0],"masksToBounds":false,"rotation":0,"scale":1,"position":{"pointX":308.833740234375,"pointY":62.80194091796875},"width":620,"sublayerTransform":[1,0,0,0,0,1,0,0,0,0,1,0,0,0,0,1],"contentsRect":{"y":0,"x":0,"width":1,"height":1},"opacity":1,"edgeAntialiasingMask":0,"height":128,"hidden":false,"anchorPoint":{"pointX":0.5,"pointY":0.5}},"texture":"599DC56368438AE14825012FB21F2616"}]}]},{"animations":[],"initialState":{"affineTransform":[1,0,0,1,0,0],"masksToBounds":false,"rotation":0,"scale":1,"position":{"pointX":960,"pointY":540},"width":1920,"sublayerTransform":[1,0,0,0,0,1,0,0,0,0,1,0,0,0,0,1],"contentsRect":{"y":0,"x":0,"width":1,"height":1},"opacity":1,"edgeAntialiasingMask":251658240,"height":1080,"hidden":false,"anchorPoint":{"pointX":0.5,"pointY":0.5}},"layers":[{"animations":[],"initialState":{"affineTransform":[1,0,0,1,0,0],"masksToBounds":false,"rotation":0,"scale":1,"position":{"pointX":1380.166259765625,"pointY":892.4183349609375},"width":620,"sublayerTransform":[1,0,0,0,0,1,0,0,0,0,1,0,0,0,0,1],"contentsRect":{"y":0,"x":0,"width":1,"height":1},"opacity":1,"edgeAntialiasingMask":251658240,"height":128,"hidden":false,"anchorPoint":{"pointX":0.5,"pointY":0.5}},"layers":[{"animations":[],"layers":[],"texturedRectangle":{"singleTextureOpacity":1,"textXHeight":0,"shapePath":{"lineWidth":1,"flatness":0.59999999999999998,"lineCapStyle":0,"elements":[{"type":"MoveToPoint","points":[[5.166259765625,5.4183349609375]]},{"type":"AddLine","points":[[614.49725341796875,5.4183349609375]]},{"type":"AddLine","points":[[614.49725341796875,122.70450592041016]]},{"type":"AddLine","points":[[5.166259765625,122.70450592041016]]},{"type":"CloseSubpath"},{"type":"MoveToPoint","points":[[5.166259765625,5.4183349609375]]}],"windingRule":0,"lineJoinStyle":0,"miterLimit":10},"isBackgroundTexture":true,"textBaseline":0,"isVerticalText":false,"textureType":5},"initialState":{"affineTransform":[1,0,0,1,0,0],"masksToBounds":false,"rotation":0,"scale":1,"position":{"pointX":308.833740234375,"pointY":62.5816650390625},"width":620,"sublayerTransform":[1,0,0,0,0,1,0,0,0,0,1,0,0,0,0,1],"contentsRect":{"y":0,"x":0,"width":1,"height":1},"opacity":1,"edgeAntialiasingMask":0,"height":128,"hidden":false,"anchorPoint":{"pointX":0.5,"pointY":0.5}},"texture":"C9F81E9FC932E0891783B87EDE7E3B6E"}]}]},{"animations":[],"initialState":{"affineTransform":[1,0,0,1,0,0],"masksToBounds":false,"rotation":0,"scale":1,"position":{"pointX":960,"pointY":540},"width":1920,"sublayerTransform":[1,0,0,0,0,1,0,0,0,0,1,0,0,0,0,1],"contentsRect":{"y":0,"x":0,"width":1,"height":1},"opacity":1,"edgeAntialiasingMask":251658240,"height":1080,"hidden":false,"anchorPoint":{"pointX":0.5,"pointY":0.5}},"layers":[{"animations":[],"initialState":{"affineTransform":[1,0,0,1,0,0],"masksToBounds":false,"rotation":0,"scale":1,"position":{"pointX":961.70493996143341,"pointY":89.746328443288803},"width":1926,"sublayerTransform":[1,0,0,0,0,1,0,0,0,0,1,0,0,0,0,1],"contentsRect":{"y":0,"x":0,"width":1,"height":1},"opacity":1,"edgeAntialiasingMask":251658240,"height":180,"hidden":false,"anchorPoint":{"pointX":0.5,"pointY":0.5}},"layers":[{"animations":[],"layers":[],"texturedRectangle":{"singleTextureOpacity":1,"textXHeight":0,"shapePath":{"lineWidth":1,"flatness":0.59999999999999998,"lineCapStyle":0,"elements":[{"type":"MoveToPoint","points":[[1.7049399614334106,1.7463284432888031]]},{"type":"AddLine","points":[[1924.2950278520584,1.7463284432888031]]},{"type":"AddLine","points":[[1924.2950278520584,178.65262421965599]]},{"type":"AddLine","points":[[1.7049399614334106,178.65262421965599]]},{"type":"CloseSubpath"},{"type":"MoveToPoint","points":[[1.7049399614334106,1.7463284432888031]]}],"windingRule":0,"lineJoinStyle":0,"miterLimit":10},"isBackgroundTexture":true,"textBaseline":0,"isVerticalText":false,"textureType":5},"initialState":{"affineTransform":[1,0,0,1,0,0],"masksToBounds":false,"rotation":0,"scale":1,"position":{"pointX":961.29506003856659,"pointY":88.253671556711197},"width":1926,"sublayerTransform":[1,0,0,0,0,1,0,0,0,0,1,0,0,0,0,1],"contentsRect":{"y":0,"x":0,"width":1,"height":1},"opacity":1,"edgeAntialiasingMask":0,"height":180,"hidden":false,"anchorPoint":{"pointX":0.5,"pointY":0.5}},"texture":"5299F162DC250DDCFDCD2A19147CC01B"}]}]},{"animations":[],"initialState":{"affineTransform":[1,0,0,1,0,0],"masksToBounds":false,"rotation":0,"scale":1,"position":{"pointX":960,"pointY":540},"width":1920,"sublayerTransform":[1,0,0,0,0,1,0,0,0,0,1,0,0,0,0,1],"contentsRect":{"y":0,"x":0,"width":1,"height":1},"opacity":1,"edgeAntialiasingMask":251658240,"height":1080,"hidden":false,"anchorPoint":{"pointX":0.5,"pointY":0.5}},"layers":[{"animations":[],"initialState":{"affineTransform":[1,0,0,1,0,0],"masksToBounds":false,"rotation":0,"scale":1,"position":{"pointX":961.30000000000007,"pointY":238.60000000000002},"width":34,"sublayerTransform":[1,0,0,0,0,1,0,0,0,0,1,0,0,0,0,1],"contentsRect":{"y":0,"x":0,"width":1,"height":1},"opacity":1,"edgeAntialiasingMask":251658240,"height":124,"hidden":false,"anchorPoint":{"pointX":0.5,"pointY":0.5}},"objectID":"B40CEB66-27F9-4E74-BF73-EE1640227C05","layers":[{"animations":[],"layers":[],"texturedRectangle":{"singleTextureOpacity":1,"textXHeight":0,"shapePath":{"lineWidth":1,"flatness":0.59999999999999998,"lineCapStyle":0,"elements":[{"type":"MoveToPoint","points":[[16.900000000000091,1.6000000000000227]]},{"type":"AddLine","points":[[16.900000000000091,91.700000000000045]]},{"type":"AddLine","points":[[16.900000000000091,95.700000000000045]]}],"windingRule":0,"lineJoinStyle":0,"miterLimit":10},"isBackgroundTexture":true,"textBaseline":0,"isVerticalText":false,"textureType":5},"initialState":{"affineTransform":[1,0,0,1,0,0],"masksToBounds":false,"rotation":0,"scale":1,"position":{"pointX":15.699999999999932,"pointY":60.399999999999977},"width":34,"sublayerTransform":[1,0,0,0,0,1,0,0,0,0,1,0,0,0,0,1],"contentsRect":{"y":0,"x":0,"width":1,"height":1},"opacity":1,"edgeAntialiasingMask":0,"height":124,"hidden":false,"anchorPoint":{"pointX":0.5,"pointY":0.5}},"texture":"0FEF2B786609238E24DCBD6FA003DA71"}]}]},{"animations":[],"initialState":{"affineTransform":[1,0,0,1,0,0],"masksToBounds":false,"rotation":0,"scale":1,"position":{"pointX":960,"pointY":540},"width":1920,"sublayerTransform":[1,0,0,0,0,1,0,0,0,0,1,0,0,0,0,1],"contentsRect":{"y":0,"x":0,"width":1,"height":1},"opacity":1,"edgeAntialiasingMask":251658240,"height":1080,"hidden":false,"anchorPoint":{"pointX":0.5,"pointY":0.5}},"layers":[{"animations":[],"initialState":{"affineTransform":[1,0,0,1,0,0],"masksToBounds":false,"rotation":0,"scale":1,"position":{"pointX":746,"pointY":494.70000000000005},"width":441,"sublayerTransform":[1,0,0,0,0,1,0,0,0,0,1,0,0,0,0,1],"contentsRect":{"y":0,"x":0,"width":1,"height":1},"opacity":1,"edgeAntialiasingMask":251658240,"height":143,"hidden":false,"anchorPoint":{"pointX":0.5,"pointY":0.5}},"objectID":"D50B8826-71B6-4A0D-9E46-08E58B3CC3F7","layers":[{"animations":[],"layers":[],"texturedRectangle":{"singleTextureOpacity":1,"textXHeight":0,"shapePath":{"lineWidth":1,"flatness":0.59999999999999998,"lineCapStyle":0,"elements":[{"type":"MoveToPoint","points":[[435.90000000000009,1.2000000000000455]]},{"type":"AddLine","points":[[435.90000000000009,68.100000000000023]]},{"type":"AddLine","points":[[17.100000000000023,68.100000000000023]]},{"type":"AddLine","points":[[17.100000000000023,109.89999999999998]]},{"type":"AddLine","points":[[17.100000000000023,113.89999999999998]]}],"windingRule":0,"lineJoinStyle":0,"miterLimit":10},"isBackgroundTexture":true,"textBaseline":0,"isVerticalText":false,"textureType":5},"initialState":{"affineTransform":[1,0,0,1,0,0],"masksToBounds":false,"rotation":0,"scale":1,"position":{"pointX":219,"pointY":70.299999999999955},"width":441,"sublayerTransform":[1,0,0,0,0,1,0,0,0,0,1,0,0,0,0,1],"contentsRect":{"y":0,"x":0,"width":1,"height":1},"opacity":1,"edgeAntialiasingMask":0,"height":143,"hidden":false,"anchorPoint":{"pointX":0.5,"pointY":0.5}},"texture":"9211CEF4A32EFCE19DDE0CF9CF6F5DB5"}]}]},{"animations":[],"initialState":{"affineTransform":[1,0,0,1,0,0],"masksToBounds":false,"rotation":0,"scale":1,"position":{"pointX":960,"pointY":540},"width":1920,"sublayerTransform":[1,0,0,0,0,1,0,0,0,0,1,0,0,0,0,1],"contentsRect":{"y":0,"x":0,"width":1,"height":1},"opacity":1,"edgeAntialiasingMask":251658240,"height":1080,"hidden":false,"anchorPoint":{"pointX":0.5,"pointY":0.5}},"layers":[{"animations":[],"initialState":{"affineTransform":[1,0,0,1,0,0],"masksToBounds":false,"rotation":0,"scale":1,"position":{"pointX":1176.9000000000001,"pointY":494.70000000000005},"width":442,"sublayerTransform":[1,0,0,0,0,1,0,0,0,0,1,0,0,0,0,1],"contentsRect":{"y":0,"x":0,"width":1,"height":1},"opacity":1,"edgeAntialiasingMask":251658240,"height":143,"hidden":false,"anchorPoint":{"pointX":0.5,"pointY":0.5}},"objectID":"DD1B31DF-6619-4B5D-8A79-8C6F30D76B17","layers":[{"animations":[],"layers":[],"texturedRectangle":{"singleTextureOpacity":1,"textXHeight":0,"shapePath":{"lineWidth":1,"flatness":0.59999999999999998,"lineCapStyle":0,"elements":[{"type":"MoveToPoint","points":[[5.9000000000000909,1.2000000000000455]]},{"type":"AddLine","points":[[5.9000000000000909,68.100000000000023]]},{"type":"AddLine","points":[[424.80000000000018,68.100000000000023]]},{"type":"AddLine","points":[[424.80000000000018,109.89999999999998]]},{"type":"AddLine","points":[[424.80000000000018,113.89999999999998]]}],"windingRule":0,"lineJoinStyle":0,"miterLimit":10},"isBackgroundTexture":true,"textBaseline":0,"isVerticalText":false,"textureType":5},"initialState":{"affineTransform":[1,0,0,1,0,0],"masksToBounds":false,"rotation":0,"scale":1,"position":{"pointX":219.09999999999991,"pointY":70.299999999999955},"width":442,"sublayerTransform":[1,0,0,0,0,1,0,0,0,0,1,0,0,0,0,1],"contentsRect":{"y":0,"x":0,"width":1,"height":1},"opacity":1,"edgeAntialiasingMask":0,"height":143,"hidden":false,"anchorPoint":{"pointX":0.5,"pointY":0.5}},"texture":"08F420D27E33D0EC9CABBBFB1CBFCF70"}]}]},{"animations":[],"initialState":{"affineTransform":[1,0,0,1,0,0],"masksToBounds":false,"rotation":0,"scale":1,"position":{"pointX":960,"pointY":540},"width":1920,"sublayerTransform":[1,0,0,0,0,1,0,0,0,0,1,0,0,0,0,1],"contentsRect":{"y":0,"x":0,"width":1,"height":1},"opacity":1,"edgeAntialiasingMask":251658240,"height":1080,"hidden":false,"anchorPoint":{"pointX":0.5,"pointY":0.5}},"layers":[{"animations":[],"initialState":{"affineTransform":[1,0,0,1,0,0],"masksToBounds":false,"rotation":0,"scale":1,"position":{"pointX":1380.2000000000003,"pointY":759.90000000000009},"width":34,"sublayerTransform":[1,0,0,0,0,1,0,0,0,0,1,0,0,0,0,1],"contentsRect":{"y":0,"x":0,"width":1,"height":1},"opacity":1,"edgeAntialiasingMask":251658240,"height":143,"hidden":false,"anchorPoint":{"pointX":0.5,"pointY":0.5}},"objectID":"71C7034D-C2C2-41A7-8910-3A95DFFF9E37","layers":[{"animations":[],"layers":[],"texturedRectangle":{"singleTextureOpacity":1,"textXHeight":0,"shapePath":{"lineWidth":1,"flatness":0.59999999999999998,"lineCapStyle":0,"elements":[{"type":"MoveToPoint","points":[[16.800000000000182,1.4000000000000909]]},{"type":"AddLine","points":[[16.800000000000182,110.20000000000005]]},{"type":"AddLine","points":[[16.800000000000182,114.20000000000005]]}],"windingRule":0,"lineJoinStyle":0,"miterLimit":10},"isBackgroundTexture":true,"textBaseline":0,"isVerticalText":false,"textureType":5},"initialState":{"affineTransform":[1,0,0,1,0,0],"masksToBounds":false,"rotation":0,"scale":1,"position":{"pointX":15.799999999999727,"pointY":70.099999999999909},"width":34,"sublayerTransform":[1,0,0,0,0,1,0,0,0,0,1,0,0,0,0,1],"contentsRect":{"y":0,"x":0,"width":1,"height":1},"opacity":1,"edgeAntialiasingMask":0,"height":143,"hidden":false,"anchorPoint":{"pointX":0.5,"pointY":0.5}},"texture":"C2A54592E8BA3E35D010F868277412E0"}]}]},{"animations":[],"initialState":{"affineTransform":[1,0,0,1,0,0],"masksToBounds":false,"rotation":0,"scale":1,"position":{"pointX":960,"pointY":540},"width":1920,"sublayerTransform":[1,0,0,0,0,1,0,0,0,0,1,0,0,0,0,1],"contentsRect":{"y":0,"x":0,"width":1,"height":1},"opacity":1,"edgeAntialiasingMask":251658240,"height":1080,"hidden":false,"anchorPoint":{"pointX":0.5,"pointY":0.5}},"layers":[{"animations":[],"initialState":{"affineTransform":[1,0,0,1,0,0],"masksToBounds":false,"rotation":0,"scale":1,"position":{"pointX":961.30000000000007,"pointY":238.60000000000002},"width":34,"sublayerTransform":[1,0,0,0,0,1,0,0,0,0,1,0,0,0,0,1],"contentsRect":{"y":0,"x":0,"width":1,"height":1},"opacity":1,"edgeAntialiasingMask":251658240,"height":124,"hidden":false,"anchorPoint":{"pointX":0.5,"pointY":0.5}},"objectID":"903782E3-C9EE-489A-81E6-A62D2A7D9449","layers":[{"animations":[],"layers":[],"texturedRectangle":{"singleTextureOpacity":1,"textXHeight":0,"shapePath":{"lineWidth":1,"flatness":0.59999999999999998,"lineCapStyle":0,"elements":[{"type":"MoveToPoint","points":[[16.900000000000091,28.800000000000011]]},{"type":"AddLine","points":[[16.900000000000091,32.800000000000011]]},{"type":"AddLine","points":[[16.900000000000091,122.90000000000003]]}],"windingRule":0,"lineJoinStyle":0,"miterLimit":10},"isBackgroundTexture":true,"textBaseline":0,"isVerticalText":false,"textureType":5},"initialState":{"affineTransform":[1,0,0,1,0,0],"masksToBounds":false,"rotation":0,"scale":1,"position":{"pointX":15.699999999999932,"pointY":60.399999999999977},"width":34,"sublayerTransform":[1,0,0,0,0,1,0,0,0,0,1,0,0,0,0,1],"contentsRect":{"y":0,"x":0,"width":1,"height":1},"opacity":1,"edgeAntialiasingMask":0,"height":124,"hidden":true,"anchorPoint":{"pointX":0.5,"pointY":0.5}},"texture":"73E42203A74861E56ECA3E130B16097A"}]}]},{"animations":[],"initialState":{"affineTransform":[1,0,0,1,0,0],"masksToBounds":false,"rotation":0,"scale":1,"position":{"pointX":960,"pointY":540},"width":1920,"sublayerTransform":[1,0,0,0,0,1,0,0,0,0,1,0,0,0,0,1],"contentsRect":{"y":0,"x":0,"width":1,"height":1},"opacity":1,"edgeAntialiasingMask":251658240,"height":1080,"hidden":false,"anchorPoint":{"pointX":0.5,"pointY":0.5}},"layers":[{"animations":[],"initialState":{"affineTransform":[1,0,0,1,0,0],"masksToBounds":false,"rotation":0,"scale":1,"position":{"pointX":757.60000000000002,"pointY":494.70000000000005},"width":441,"sublayerTransform":[1,0,0,0,0,1,0,0,0,0,1,0,0,0,0,1],"contentsRect":{"y":0,"x":0,"width":1,"height":1},"opacity":1,"edgeAntialiasingMask":251658240,"height":143,"hidden":false,"anchorPoint":{"pointX":0.5,"pointY":0.5}},"objectID":"AE2C191D-1DEF-4609-88E0-7F29F0EAF20C","layers":[{"animations":[],"layers":[],"texturedRectangle":{"singleTextureOpacity":1,"textXHeight":0,"shapePath":{"lineWidth":1,"flatness":0.59999999999999998,"lineCapStyle":0,"elements":[{"type":"MoveToPoint","points":[[423.90000000000009,28.400000000000034]]},{"type":"AddLine","points":[[423.90000000000009,32.400000000000034]]},{"type":"AddLine","points":[[423.90000000000009,68.100000000000023]]},{"type":"AddLine","points":[[5.1000000000000227,68.100000000000023]]},{"type":"AddLine","points":[[5.1000000000000227,141.10000000000002]]}],"windingRule":0,"lineJoinStyle":0,"miterLimit":10},"isBackgroundTexture":true,"textBaseline":0,"isVerticalText":false,"textureType":5},"initialState":{"affineTransform":[1,0,0,1,0,0],"masksToBounds":false,"rotation":0,"scale":1,"position":{"pointX":219.39999999999998,"pointY":70.299999999999955},"width":441,"sublayerTransform":[1,0,0,0,0,1,0,0,0,0,1,0,0,0,0,1],"contentsRect":{"y":0,"x":0,"width":1,"height":1},"opacity":1,"edgeAntialiasingMask":0,"height":143,"hidden":true,"anchorPoint":{"pointX":0.5,"pointY":0.5}},"texture":"D4535E46D712DA438D540C50849987E9"}]}]},{"animations":[],"initialState":{"affineTransform":[1,0,0,1,0,0],"masksToBounds":false,"rotation":0,"scale":1,"position":{"pointX":960,"pointY":540},"width":1920,"sublayerTransform":[1,0,0,0,0,1,0,0,0,0,1,0,0,0,0,1],"contentsRect":{"y":0,"x":0,"width":1,"height":1},"opacity":1,"edgeAntialiasingMask":251658240,"height":1080,"hidden":false,"anchorPoint":{"pointX":0.5,"pointY":0.5}},"layers":[{"animations":[],"initialState":{"affineTransform":[1,0,0,1,0,0],"masksToBounds":false,"rotation":0,"scale":1,"position":{"pointX":1164.8000000000002,"pointY":494.70000000000005},"width":441,"sublayerTransform":[1,0,0,0,0,1,0,0,0,0,1,0,0,0,0,1],"contentsRect":{"y":0,"x":0,"width":1,"height":1},"opacity":1,"edgeAntialiasingMask":251658240,"height":143,"hidden":false,"anchorPoint":{"pointX":0.5,"pointY":0.5}},"objectID":"6AA4FBB7-6B28-4C94-8B13-9A1D63CDD70F","layers":[{"animations":[],"layers":[],"texturedRectangle":{"singleTextureOpacity":1,"textXHeight":0,"shapePath":{"lineWidth":1,"flatness":0.59999999999999998,"lineCapStyle":0,"elements":[{"type":"MoveToPoint","points":[[16.900000000000091,28.400000000000034]]},{"type":"AddLine","points":[[16.900000000000091,32.400000000000034]]},{"type":"AddLine","points":[[16.900000000000091,68.100000000000023]]},{"type":"AddLine","points":[[435.80000000000018,68.100000000000023]]},{"type":"AddLine","points":[[435.80000000000018,141.10000000000002]]}],"windingRule":0,"lineJoinStyle":0,"miterLimit":10},"isBackgroundTexture":true,"textBaseline":0,"isVerticalText":false,"textureType":5},"initialState":{"affineTransform":[1,0,0,1,0,0],"masksToBounds":false,"rotation":0,"scale":1,"position":{"pointX":219.19999999999993,"pointY":70.299999999999955},"width":441,"sublayerTransform":[1,0,0,0,0,1,0,0,0,0,1,0,0,0,0,1],"contentsRect":{"y":0,"x":0,"width":1,"height":1},"opacity":1,"edgeAntialiasingMask":0,"height":143,"hidden":true,"anchorPoint":{"pointX":0.5,"pointY":0.5}},"texture":"DBD44AC5EC23EE3DF080EA173AE7C574"}]}]},{"animations":[],"initialState":{"affineTransform":[1,0,0,1,0,0],"masksToBounds":false,"rotation":0,"scale":1,"position":{"pointX":960,"pointY":540},"width":1920,"sublayerTransform":[1,0,0,0,0,1,0,0,0,0,1,0,0,0,0,1],"contentsRect":{"y":0,"x":0,"width":1,"height":1},"opacity":1,"edgeAntialiasingMask":251658240,"height":1080,"hidden":false,"anchorPoint":{"pointX":0.5,"pointY":0.5}},"layers":[{"animations":[],"initialState":{"affineTransform":[1,0,0,1,0,0],"masksToBounds":false,"rotation":0,"scale":1,"position":{"pointX":1380.2000000000003,"pointY":759.90000000000009},"width":34,"sublayerTransform":[1,0,0,0,0,1,0,0,0,0,1,0,0,0,0,1],"contentsRect":{"y":0,"x":0,"width":1,"height":1},"opacity":1,"edgeAntialiasingMask":251658240,"height":143,"hidden":false,"anchorPoint":{"pointX":0.5,"pointY":0.5}},"objectID":"BDEFA4D4-23C8-47F1-8AD2-9A3A16CC66F4","layers":[{"animations":[],"layers":[],"texturedRectangle":{"singleTextureOpacity":1,"textXHeight":0,"shapePath":{"lineWidth":1,"flatness":0.59999999999999998,"lineCapStyle":0,"elements":[{"type":"MoveToPoint","points":[[16.800000000000182,28.600000000000136]]},{"type":"AddLine","points":[[16.800000000000182,32.600000000000136]]},{"type":"AddLine","points":[[16.800000000000182,141.40000000000009]]}],"windingRule":0,"lineJoinStyle":0,"miterLimit":10},"isBackgroundTexture":true,"textBaseline":0,"isVerticalText":false,"textureType":5},"initialState":{"affineTransform":[1,0,0,1,0,0],"masksToBounds":false,"rotation":0,"scale":1,"position":{"pointX":15.799999999999727,"pointY":70.099999999999909},"width":34,"sublayerTransform":[1,0,0,0,0,1,0,0,0,0,1,0,0,0,0,1],"contentsRect":{"y":0,"x":0,"width":1,"height":1},"opacity":1,"edgeAntialiasingMask":0,"height":143,"hidden":true,"anchorPoint":{"pointX":0.5,"pointY":0.5}},"texture":"370936F4C116E35A4E4E20C10E9D5053"}]}]}]}},{"effects":[{"beginTime":0,"baseLayer":{"animations":[],"initialState":{"affineTransform":[1,0,0,1,0,0],"masksToBounds":false,"rotation":0,"scale":1,"position":{"pointX":960,"pointY":540},"width":1920,"sublayerTransform":[1,0,0,0,0,1,0,0,0,0,1,0,0,0,0,1],"contentsRect":{"y":0,"x":0,"width":1,"height":1},"opacity":1,"edgeAntialiasingMask":251658240,"height":1080,"hidden":false,"anchorPoint":{"pointX":0.5,"pointY":0.5}},"objectID":"0","layers":[{"animations":[],"initialState":{"affineTransform":[1,0,0,1,0,0],"masksToBounds":false,"rotation":0,"scale":1,"position":{"pointX":960,"pointY":540},"width":1920,"sublayerTransform":[1,0,0,0,0,1,0,0,0,0,1,-0.00035007912466775983,0,0,0,1],"contentsRect":{"y":0,"x":0,"width":1,"height":1},"opacity":1,"edgeAntialiasingMask":251658240,"height":1080,"hidden":false,"anchorPoint":{"pointX":0.5,"pointY":0.5}},"layers":[{"animations":[],"layers":[],"texturedRectangle":{"isBackgroundTexture":false,"singleTextureOpacity":1,"textureType":0,"textBaseline":0,"textXHeight":0,"isVerticalText":false},"initialState":{"affineTransform":[1,0,0,1,0,0],"masksToBounds":false,"rotation":0,"scale":1,"position":{"pointX":960,"pointY":540},"width":1920,"sublayerTransform":[1,0,0,0,0,1,0,0,0,0,1,0,0,0,0,1],"contentsRect":{"y":0,"x":0,"width":1,"height":1},"opacity":1,"edgeAntialiasingMask":0,"height":1080,"hidden":false,"anchorPoint":{"pointX":0.5,"pointY":0.5}},"texture":"BD818B1FEA8AC6E7E678F89C18F5D64B"},{"animations":[{"timeOffset":0,"from":{"scalar":false},"beginTime":0,"repeatCount":0,"fillMode":"both","property":"hidden","autoreverses":false,"duration":0.01,"to":{"scalar":true}}],"layers":[],"texturedRectangle":{"isBackgroundTexture":false,"singleTextureOpacity":1,"textureType":0,"textBaseline":0,"textXHeight":0,"isVerticalText":false},"initialState":{"affineTransform":[1,0,0,1,0,0],"masksToBounds":false,"rotation":0,"scale":1,"position":{"pointX":960,"pointY":540},"width":1920,"sublayerTransform":[1,0,0,0,0,1,0,0,0,0,1,0,0,0,0,1],"contentsRect":{"y":0,"x":0,"width":1,"height":1},"opacity":1,"edgeAntialiasingMask":0,"height":1080,"hidden":false,"anchorPoint":{"pointX":0.5,"pointY":0.5}},"texture":"65279477319C7AF4FE443308577C43EE"}]}]},"effects":[],"duration":0.01,"type":"transition","name":"none","objectID":"0"}],"automaticPlay":false,"hyperlinks":[],"accessibility":[{"text":"<search-movies-box\/>","targetRectangle":{"y":601.19805908203125,"x":319.39675903320312,"width":443.54296875,"height":50}},{"text":"<movies-list\/>","targetRectangle":{"y":601.19805908203125,"x":1238.7633972167969,"width":280.13671875,"height":50}},{"text":"<movies-list-item\/>","targetRectangle":{"y":866.4183349609375,"x":1188.5910339355469,"width":380.4814453125,"height":50}},{"text":"<search-movies-page\/>","targetRectangle":{"y":335.97772216796875,"x":726.54928588867188,"width":466.9013671875,"height":50}},{"text":"outside world","targetRectangle":{"y":57.746328443288803,"x":761.20310890674591,"width":397.59375,"height":61.5703125}}],"baseLayer":{"animations":[],"initialState":{"affineTransform":[1,0,0,1,0,0],"masksToBounds":false,"rotation":0,"scale":1,"position":{"pointX":960,"pointY":540},"width":1920,"sublayerTransform":[1,0,0,0,0,1,0,0,0,0,1,0,0,0,0,1],"contentsRect":{"y":0,"x":0,"width":1,"height":1},"opacity":1,"edgeAntialiasingMask":251658240,"height":1080,"hidden":false,"anchorPoint":{"pointX":0.5,"pointY":0.5}},"objectID":"0","layers":[{"animations":[],"initialState":{"affineTransform":[1,0,0,1,0,0],"masksToBounds":false,"rotation":0,"scale":1,"position":{"pointX":960,"pointY":540},"width":1920,"sublayerTransform":[1,0,0,0,0,1,0,0,0,0,1,-0.00035007912466775983,0,0,0,1],"contentsRect":{"y":0,"x":0,"width":1,"height":1},"opacity":1,"edgeAntialiasingMask":251658240,"height":1080,"hidden":false,"anchorPoint":{"pointX":0.5,"pointY":0.5}},"layers":[{"animations":[],"layers":[],"texturedRectangle":{"isBackgroundTexture":false,"singleTextureOpacity":1,"textureType":0,"textBaseline":0,"textXHeight":0,"isVerticalText":false},"initialState":{"affineTransform":[1,0,0,1,0,0],"masksToBounds":false,"rotation":0,"scale":1,"position":{"pointX":960,"pointY":540},"width":1920,"sublayerTransform":[1,0,0,0,0,1,0,0,0,0,1,0,0,0,0,1],"contentsRect":{"y":0,"x":0,"width":1,"height":1},"opacity":1,"edgeAntialiasingMask":0,"height":1080,"hidden":false,"anchorPoint":{"pointX":0.5,"pointY":0.5}},"texture":"65279477319C7AF4FE443308577C43EE"}]}]}}]}